{"data":[{"id":2,"unique_id":"1pUzdZs61m","name":null,"username":"\u5742\u672c \u76f4\u5b50","email":"tomoya.miyake@example.org","unique_id_search_flag":1,"username_search_flag":1,"permitted":null,"attribute":{"id":8,"manager":{"id":2,"unique_id":"1pUzdZs61m","name":null,"username":"\u5742\u672c \u76f4\u5b50","email":"tomoya.miyake@example.org","unique_id_search_flag":1,"username_search_flag":1,"created_at":{"date":"2019-02-24 09:05:54.000000","timezone_type":3,"timezone":"UTC"},"updated_at":{"date":"2019-02-24 09:05:54.000000","timezone_type":3,"timezone":"UTC"},"deleted_at":null},"name":"eius","plus_minus":933,"created_at":{"date":"2019-02-24 09:05:54.000000","timezone_type":3,"timezone":"UTC"},"updated_at":{"date":"2019-02-24 09:05:54.000000","timezone_type":3,"timezone":"UTC"},"deleted_at":null},"created_at":{"date":"2019-02-24 09:05:54.000000","timezone_type":3,"timezone":"UTC"},"updated_at":{"date":"2019-02-24 09:05:54.000000","timezone_type":3,"timezone":"UTC"},"deleted_at":null},{"id":23,"unique_id":"d7inrsXTwg","name":null,"username":"\u5de5\u85e4 \u3042\u3059\u304b","email":"kiriyama.sayuri@example.net","unique_id_search_flag":1,"username_search_flag":1,"permitted":null,"attribute":{"id":111,"manager":{"id":23,"unique_id":"d7inrsXTwg","name":null,"username":"\u5de5\u85e4 \u3042\u3059\u304b","email":"kiriyama.sayuri@example.net","unique_id_search_flag":1,"username_search_flag":1,"created_at":{"date":"2019-02-24 09:05:54.000000","timezone_type":3,"timezone":"UTC"},"updated_at":{"date":"2019-02-24 09:05:54.000000","timezone_type":3,"timezone":"UTC"},"deleted_at":null},"name":"cumque","plus_minus":991,"created_at":{"date":"2019-02-24 09:06:03.000000","timezone_type":3,"timezone":"UTC"},"updated_at":{"date":"2019-02-24 09:06:03.000000","timezone_type":3,"timezone":"UTC"},"deleted_at":null},"created_at":{"date":"2019-02-24 09:05:54.000000","timezone_type":3,"timezone":"UTC"},"updated_at":{"date":"2019-02-24 09:05:54.000000","timezone_type":3,"timezone":"UTC"},"deleted_at":null},{"id":24,"unique_id":"bBqeeiyGO2","name":null,"username":"\u5c71\u7530 \u96f6","email":"lkiriyama@example.org","unique_id_search_flag":1,"username_search_flag":1,"permitted":null,"attribute":{"id":120,"manager":{"id":24,"unique_id":"bBqeeiyGO2","name":null,"username":"\u5c71\u7530 \u96f6","email":"lkiriyama@example.org","unique_id_search_flag":1,"username_search_flag":1,"created_at":{"date":"2019-02-24 09:05:54.000000","timezone_type":3,"timezone":"UTC"},"updated_at":{"date":"2019-02-24 09:05:54.000000","timezone_type":3,"timezone":"UTC"},"deleted_at":null},"name":"optio","plus_minus":2329,"created_at":{"date":"2019-02-24 09:06:04.000000","timezone_type":3,"timezone":"UTC"},"updated_at":{"date":"2019-02-24 09:06:04.000000","timezone_type":3,"timezone":"UTC"},"deleted_at":null},"created_at":{"date":"2019-02-24 09:05:54.000000","timezone_type":3,"timezone":"UTC"},"updated_at":{"date":"2019-02-24 09:05:54.000000","timezone_type":3,"timezone":"UTC"},"deleted_at":null},{"id":27,"unique_id":"XkyehHCt7k","name":null,"username":"\u85e4\u672c \u6843\u5b50","email":"kazuya87@example.com","unique_id_search_flag":1,"username_search_flag":1,"permitted":null,"attribute":{"id":133,"manager":{"id":27,"unique_id":"XkyehHCt7k","name":null,"username":"\u85e4\u672c \u6843\u5b50","email":"kazuya87@example.com","unique_id_search_flag":1,"username_search_flag":1,"created_at":{"date":"2019-02-24 09:05:54.000000","timezone_type":3,"timezone":"UTC"},"updated_at":{"date":"2019-02-24 09:05:54.000000","timezone_type":3,"timezone":"UTC"},"deleted_at":null},"name":"impedit","plus_minus":2170,"created_at":{"date":"2019-02-24 09:06:05.000000","timezone_type":3,"timezone":"UTC"},"updated_at":{"date":"2019-02-24 09:06:05.000000","timezone_type":3,"timezone":"UTC"},"deleted_at":null},"created_at":{"date":"2019-02-24 09:05:54.000000","timezone_type":3,"timezone":"UTC"},"updated_at":{"date":"2019-02-24 09:05:54.000000","timezone_type":3,"timezone":"UTC"},"deleted_at":null},{"id":29,"unique_id":"dF8uyo6WEu","name":null,"username":"\u5c0f\u6797 \u82b1\u5b50","email":"yoko.matsumoto@example.org","unique_id_search_flag":1,"username_search_flag":1,"permitted":null,"attribute":{"id":144,"manager":{"id":29,"unique_id":"dF8uyo6WEu","name":null,"username":"\u5c0f\u6797 \u82b1\u5b50","email":"yoko.matsumoto@example.org","unique_id_search_flag":1,"username_search_flag":1,"created_at":{"date":"2019-02-24 09:05:54.000000","timezone_type":3,"timezone":"UTC"},"updated_at":{"date":"2019-02-24 09:05:54.000000","timezone_type":3,"timezone":"UTC"},"deleted_at":null},"name":"iusto","plus_minus":-287,"created_at":{"date":"2019-02-24 09:06:06.000000","timezone_type":3,"timezone":"UTC"},"updated_at":{"date":"2019-02-24 09:06:06.000000","timezone_type":3,"timezone":"UTC"},"deleted_at":null},"created_at":{"date":"2019-02-24 09:05:54.000000","timezone_type":3,"timezone":"UTC"},"updated_at":{"date":"2019-02-24 09:05:54.000000","timezone_type":3,"timezone":"UTC"},"deleted_at":null},{"id":30,"unique_id":"I3WSr8Te0J","name":null,"username":"\u9ad8\u6a4b \u91cc\u4f73","email":"taichi33@example.net","unique_id_search_flag":1,"username_search_flag":1,"permitted":null,"attribute":{"id":148,"manager":{"id":30,"unique_id":"I3WSr8Te0J","name":null,"username":"\u9ad8\u6a4b \u91cc\u4f73","email":"taichi33@example.net","unique_id_search_flag":1,"username_search_flag":1,"created_at":{"date":"2019-02-24 09:05:54.000000","timezone_type":3,"timezone":"UTC"},"updated_at":{"date":"2019-02-24 09:05:54.000000","timezone_type":3,"timezone":"UTC"},"deleted_at":null},"name":"accusantium","plus_minus":-543,"created_at":{"date":"2019-02-24 09:06:06.000000","timezone_type":3,"timezone":"UTC"},"updated_at":{"date":"2019-02-24 09:06:06.000000","timezone_type":3,"timezone":"UTC"},"deleted_at":null},"created_at":{"date":"2019-02-24 09:05:54.000000","timezone_type":3,"timezone":"UTC"},"updated_at":{"date":"2019-02-24 09:05:54.000000","timezone_type":3,"timezone":"UTC"},"deleted_at":null},{"id":37,"unique_id":"wF6geieAJe","name":null,"username":"\u5c71\u672c \u667a\u4e5f","email":"murayama.satomi@example.org","unique_id_search_flag":1,"username_search_flag":1,"permitted":null,"attribute":{"id":181,"manager":{"id":37,"unique_id":"wF6geieAJe","name":null,"username":"\u5c71\u672c \u667a\u4e5f","email":"murayama.satomi@example.org","unique_id_search_flag":1,"username_search_flag":1,"created_at":{"date":"2019-02-24 09:05:54.000000","timezone_type":3,"timezone":"UTC"},"updated_at":{"date":"2019-02-24 09:05:54.000000","timezone_type":3,"timezone":"UTC"},"deleted_at":null},"name":"fugit","plus_minus":-2664,"created_at":{"date":"2019-02-24 09:06:09.000000","timezone_type":3,"timezone":"UTC"},"updated_at":{"date":"2019-02-24 09:06:09.000000","timezone_type":3,"timezone":"UTC"},"deleted_at":null},"created_at":{"date":"2019-02-24 09:05:54.000000","timezone_type":3,"timezone":"UTC"},"updated_at":{"date":"2019-02-24 09:05:54.000000","timezone_type":3,"timezone":"UTC"},"deleted_at":null},{"id":44,"unique_id":"EXJCNecHGw","name":null,"username":"\u82e5\u677e \u52a0\u5948","email":"jun10@example.net","unique_id_search_flag":1,"username_search_flag":1,"permitted":null,"attribute":{"id":220,"manager":{"id":44,"unique_id":"EXJCNecHGw","name":null,"username":"\u82e5\u677e \u52a0\u5948","email":"jun10@example.net","unique_id_search_flag":1,"username_search_flag":1,"created_at":{"date":"2019-02-24 09:05:54.000000","timezone_type":3,"timezone":"UTC"},"updated_at":{"date":"2019-02-24 09:05:54.000000","timezone_type":3,"timezone":"UTC"},"deleted_at":null},"name":"dignissimos","plus_minus":2993,"created_at":{"date":"2019-02-24 09:06:12.000000","timezone_type":3,"timezone":"UTC"},"updated_at":{"date":"2019-02-24 09:06:12.000000","timezone_type":3,"timezone":"UTC"},"deleted_at":null},"created_at":{"date":"2019-02-24 09:05:54.000000","timezone_type":3,"timezone":"UTC"},"updated_at":{"date":"2019-02-24 09:05:54.000000","timezone_type":3,"timezone":"UTC"},"deleted_at":null},{"id":46,"unique_id":"nt7F0TuFHe","name":null,"username":"\u5409\u672c \u771f\u7dbe","email":"takahashi.hanako@example.org","unique_id_search_flag":1,"username_search_flag":1,"permitted":null,"attribute":{"id":227,"manager":{"id":46,"unique_id":"nt7F0TuFHe","name":null,"username":"\u5409\u672c \u771f\u7dbe","email":"takahashi.hanako@example.org","unique_id_search_flag":1,"username_search_flag":1,"created_at":{"date":"2019-02-24 09:05:54.000000","timezone_type":3,"timezone":"UTC"},"updated_at":{"date":"2019-02-24 09:05:54.000000","timezone_type":3,"timezone":"UTC"},"deleted_at":null},"name":"perspiciatis","plus_minus":-1509,"created_at":{"date":"2019-02-24 09:06:13.000000","timezone_type":3,"timezone":"UTC"},"updated_at":{"date":"2019-02-24 09:06:13.000000","timezone_type":3,"timezone":"UTC"},"deleted_at":null},"created_at":{"date":"2019-02-24 09:05:54.000000","timezone_type":3,"timezone":"UTC"},"updated_at":{"date":"2019-02-24 09:05:54.000000","timezone_type":3,"timezone":"UTC"},"deleted_at":null},{"id":49,"unique_id":"qbs0wIIYs6","name":null,"username":"\u677e\u672c \u7a14","email":"youichi81@example.com","unique_id_search_flag":1,"username_search_flag":1,"permitted":null,"attribute":{"id":241,"manager":{"id":49,"unique_id":"qbs0wIIYs6","name":null,"username":"\u677e\u672c \u7a14","email":"youichi81@example.com","unique_id_search_flag":1,"username_search_flag":1,"created_at":{"date":"2019-02-24 09:05:54.000000","timezone_type":3,"timezone":"UTC"},"updated_at":{"date":"2019-02-24 09:05:54.000000","timezone_type":3,"timezone":"UTC"},"deleted_at":null},"name":"libero","plus_minus":801,"created_at":{"date":"2019-02-24 09:06:14.000000","timezone_type":3,"timezone":"UTC"},"updated_at":{"date":"2019-02-24 09:06:14.000000","timezone_type":3,"timezone":"UTC"},"deleted_at":null},"created_at":{"date":"2019-02-24 09:05:54.000000","timezone_type":3,"timezone":"UTC"},"updated_at":{"date":"2019-02-24 09:05:54.000000","timezone_type":3,"timezone":"UTC"},"deleted_at":null}]}