{"data":[{"id":55,"unique_id":"C4XHU3GMu2","username":"aaaa","email":"232RE@new.com","permitted":null,"attribute_id":null,"created_at":{"date":"2019-02-10 13:50:15.000000","timezone_type":3,"timezone":"UTC"},"updated_at":{"date":"2019-02-10 13:50:15.000000","timezone_type":3,"timezone":"UTC"}},{"id":57,"unique_id":"3osZiaq9Hr","username":"aaaa","email":"ntTggoK@new.com","permitted":null,"attribute_id":null,"created_at":{"date":"2019-02-10 13:50:15.000000","timezone_type":3,"timezone":"UTC"},"updated_at":{"date":"2019-02-10 13:50:15.000000","timezone_type":3,"timezone":"UTC"}},{"id":63,"unique_id":"6elWDk0nvS","username":"aaaa","email":"kFwvX@new.com","permitted":null,"attribute_id":null,"created_at":{"date":"2019-02-10 13:50:56.000000","timezone_type":3,"timezone":"UTC"},"updated_at":{"date":"2019-02-10 13:50:56.000000","timezone_type":3,"timezone":"UTC"}},{"id":65,"unique_id":"mV47oH6Edz","username":"aaaa","email":"XUFBYCB@new.com","permitted":null,"attribute_id":null,"created_at":{"date":"2019-02-10 13:50:56.000000","timezone_type":3,"timezone":"UTC"},"updated_at":{"date":"2019-02-10 13:50:56.000000","timezone_type":3,"timezone":"UTC"}},{"id":71,"unique_id":"08bXjVVLYC","username":"aaaa","email":"zCISX@new.com","permitted":null,"attribute_id":null,"created_at":{"date":"2019-02-10 13:53:35.000000","timezone_type":3,"timezone":"UTC"},"updated_at":{"date":"2019-02-10 13:53:35.000000","timezone_type":3,"timezone":"UTC"}},{"id":73,"unique_id":"804bqWvPDJ","username":"aaaa","email":"IYstjMs@new.com","permitted":null,"attribute_id":null,"created_at":{"date":"2019-02-10 13:53:35.000000","timezone_type":3,"timezone":"UTC"},"updated_at":{"date":"2019-02-10 13:53:35.000000","timezone_type":3,"timezone":"UTC"}},{"id":79,"unique_id":"ERugtJuAlC","username":"aaaa","email":"ndU55@new.com","permitted":null,"attribute_id":null,"created_at":{"date":"2019-02-10 14:00:09.000000","timezone_type":3,"timezone":"UTC"},"updated_at":{"date":"2019-02-10 14:00:09.000000","timezone_type":3,"timezone":"UTC"}},{"id":81,"unique_id":"q7s0wwoxRO","username":"aaaa","email":"51WGWFz@new.com","permitted":null,"attribute_id":null,"created_at":{"date":"2019-02-10 14:00:09.000000","timezone_type":3,"timezone":"UTC"},"updated_at":{"date":"2019-02-10 14:00:09.000000","timezone_type":3,"timezone":"UTC"}}]}