{"data":[{"id":67,"username":"aaaa","email":"I5JEM@new.com","permitted":null,"attribute_id":null,"created_at":{"date":"2019-02-09 11:39:53.000000","timezone_type":3,"timezone":"UTC"},"updated_at":{"date":"2019-02-09 11:39:53.000000","timezone_type":3,"timezone":"UTC"}},{"id":69,"username":"aaaa","email":"fkcjd5m@new.com","permitted":null,"attribute_id":null,"created_at":{"date":"2019-02-09 11:39:53.000000","timezone_type":3,"timezone":"UTC"},"updated_at":{"date":"2019-02-09 11:39:53.000000","timezone_type":3,"timezone":"UTC"}}]}