{"data":{"id":66,"name":"facilis","shop_id":"955","budget":28661,"actual":26912,"start_time":"1989-11-08 15:42:13","end_time":null,"manager":{"id":17,"unique_id":"tJAWOVxkBg","name":null,"username":"\u5c71\u7530 \u6cbb","email":"kyosuke.uno@example.com","unique_id_search_flag":1,"username_search_flag":1,"created_at":{"date":"2019-02-21 08:52:57.000000","timezone_type":3,"timezone":"UTC"},"updated_at":{"date":"2019-02-21 08:52:57.000000","timezone_type":3,"timezone":"UTC"},"deleted_at":null},"users":[{"id":1,"unique_id":"TESTTEST","name":null,"username":"\u30c6\u30b9\u30c8\u592a\u90ce","email":"testuser@example.com","unique_id_search_flag":1,"username_search_flag":1,"join_status":"deny","paid":null,"plus_minus":null,"budget":null,"budget_actual":null,"created_at":{"date":"2019-02-21 08:52:57.000000","timezone_type":3,"timezone":"UTC"},"updated_at":{"date":"2019-02-21 08:53:18.000000","timezone_type":3,"timezone":"UTC"},"deleted_at":null},{"id":4,"unique_id":"hc9Jcb2Dgx","name":null,"username":"\u5c71\u672c \u3042\u3059\u304b","email":"kenichi61@example.org","unique_id_search_flag":1,"username_search_flag":1,"join_status":"wait","paid":null,"plus_minus":null,"budget":null,"budget_actual":null,"created_at":{"date":"2019-02-21 08:52:57.000000","timezone_type":3,"timezone":"UTC"},"updated_at":{"date":"2019-02-21 08:52:57.000000","timezone_type":3,"timezone":"UTC"},"deleted_at":null},{"id":13,"unique_id":"M2ZpVrGlzI","name":null,"username":"\u677e\u672c \u6df3","email":"kobayashi.mikako@example.org","unique_id_search_flag":1,"username_search_flag":1,"join_status":"allow","paid":1,"plus_minus":null,"budget":null,"budget_actual":null,"created_at":{"date":"2019-02-21 08:52:57.000000","timezone_type":3,"timezone":"UTC"},"updated_at":{"date":"2019-02-21 08:52:57.000000","timezone_type":3,"timezone":"UTC"},"deleted_at":null},{"id":27,"unique_id":"Wx5uvXGVqb","name":null,"username":"\u85e4\u672c \u548c\u4e5f","email":"hirokawa.tomoya@example.com","unique_id_search_flag":1,"username_search_flag":1,"join_status":"deny","paid":null,"plus_minus":null,"budget":null,"budget_actual":null,"created_at":{"date":"2019-02-21 08:52:57.000000","timezone_type":3,"timezone":"UTC"},"updated_at":{"date":"2019-02-21 08:52:57.000000","timezone_type":3,"timezone":"UTC"},"deleted_at":null},{"id":29,"unique_id":"hqmNc29RN4","name":null,"username":"\u4e2d\u6751 \u6dbc\u5e73","email":"tsubasa51@example.org","unique_id_search_flag":1,"username_search_flag":1,"join_status":"allow","paid":1,"plus_minus":null,"budget":null,"budget_actual":null,"created_at":{"date":"2019-02-21 08:52:57.000000","timezone_type":3,"timezone":"UTC"},"updated_at":{"date":"2019-02-21 08:52:57.000000","timezone_type":3,"timezone":"UTC"},"deleted_at":null}],"created_at":{"date":"2019-02-21 08:53:03.000000","timezone_type":3,"timezone":"UTC"},"updated_at":{"date":"2019-02-21 08:53:03.000000","timezone_type":3,"timezone":"UTC"},"deleted_at":null}}