{"data":[{"id":12,"name":"fugit","shop_id":"J000109445","budget":23560,"actual":40084,"start_time":"2019-02-25 15:26:08","end_time":null,"unit_rounding_budget":"100","unit_rounding_actual":"100","manager":{"id":9,"unique_id":"LOewqSn5dZ","name":null,"username":"\u5c0f\u6797 \u592a\u4e00","email":"kudo.yuki@example.net","unique_id_search_flag":1,"username_search_flag":1,"created_at":{"date":"2019-03-02 15:26:06.000000","timezone_type":3,"timezone":"UTC"},"updated_at":{"date":"2019-03-02 15:26:06.000000","timezone_type":3,"timezone":"UTC"},"deleted_at":null},"users":[{"id":7,"unique_id":"CORWNToj6v","name":null,"username":"\u30c6\u30b9\u30c8\u592a\u90ce","email":"testuser@example.com","unique_id_search_flag":1,"username_search_flag":1,"join_status":"deny","paid":0,"plus_minus":null,"attribute_name":null,"budget":null,"budget_actual":null,"created_at":{"date":"2019-03-02 15:26:06.000000","timezone_type":3,"timezone":"UTC"},"updated_at":{"date":"2019-03-02 15:26:28.000000","timezone_type":3,"timezone":"UTC"},"deleted_at":null},{"id":8,"unique_id":"YQctNEoTyq","name":null,"username":"\u5409\u672c \u3055\u3086\u308a","email":"akira.yoshida@example.org","unique_id_search_flag":1,"username_search_flag":1,"join_status":"allow","paid":0,"plus_minus":null,"attribute_name":null,"budget":null,"budget_actual":null,"created_at":{"date":"2019-03-02 15:26:06.000000","timezone_type":3,"timezone":"UTC"},"updated_at":{"date":"2019-03-02 15:26:06.000000","timezone_type":3,"timezone":"UTC"},"deleted_at":null},{"id":31,"unique_id":"Xk5awqONnv","name":null,"username":"\u6d25\u7530 \u77e5\u5b9f","email":"aota.rika@example.com","unique_id_search_flag":1,"username_search_flag":1,"join_status":"deny","paid":0,"plus_minus":null,"attribute_name":null,"budget":null,"budget_actual":null,"created_at":{"date":"2019-03-02 15:26:06.000000","timezone_type":3,"timezone":"UTC"},"updated_at":{"date":"2019-03-02 15:26:06.000000","timezone_type":3,"timezone":"UTC"},"deleted_at":null},{"id":32,"unique_id":"Fj11bKTpyv","name":null,"username":"\u9234\u6728 \u967d\u5b50","email":"kenichi00@example.org","unique_id_search_flag":1,"username_search_flag":1,"join_status":"deny","paid":0,"plus_minus":null,"attribute_name":null,"budget":null,"budget_actual":null,"created_at":{"date":"2019-03-02 15:26:06.000000","timezone_type":3,"timezone":"UTC"},"updated_at":{"date":"2019-03-02 15:26:06.000000","timezone_type":3,"timezone":"UTC"},"deleted_at":null},{"id":33,"unique_id":"RHhUzYySDY","name":null,"username":"\u5b87\u91ce \u91cc\u4f73","email":"tanaka.yuta@example.org","unique_id_search_flag":1,"username_search_flag":1,"join_status":"wait","paid":0,"plus_minus":null,"attribute_name":null,"budget":null,"budget_actual":null,"created_at":{"date":"2019-03-02 15:26:06.000000","timezone_type":3,"timezone":"UTC"},"updated_at":{"date":"2019-03-02 15:26:06.000000","timezone_type":3,"timezone":"UTC"},"deleted_at":null},{"id":39,"unique_id":"I49iMbtdnq","name":null,"username":"\u5c71\u672c \u967d\u5b50","email":"anagisa@example.org","unique_id_search_flag":1,"username_search_flag":1,"join_status":"wait","paid":0,"plus_minus":null,"attribute_name":null,"budget":null,"budget_actual":null,"created_at":{"date":"2019-03-02 15:26:06.000000","timezone_type":3,"timezone":"UTC"},"updated_at":{"date":"2019-03-02 15:26:06.000000","timezone_type":3,"timezone":"UTC"},"deleted_at":null},{"id":46,"unique_id":"th59RZVqKd","name":null,"username":"\u5409\u7530 \u4e03\u590f","email":"uno.kyosuke@example.org","unique_id_search_flag":1,"username_search_flag":1,"join_status":"deny","paid":0,"plus_minus":null,"attribute_name":null,"budget":null,"budget_actual":null,"created_at":{"date":"2019-03-02 15:26:06.000000","timezone_type":3,"timezone":"UTC"},"updated_at":{"date":"2019-03-02 15:26:06.000000","timezone_type":3,"timezone":"UTC"},"deleted_at":null}],"created_at":{"date":"2019-03-02 15:26:08.000000","timezone_type":3,"timezone":"UTC"},"updated_at":{"date":"2019-03-02 15:26:08.000000","timezone_type":3,"timezone":"UTC"},"deleted_at":null},{"id":26,"name":"accusantium","shop_id":"J001182216","budget":15751,"actual":26499,"start_time":"2019-03-07 15:26:09","end_time":"2019-03-12 15:26:09","unit_rounding_budget":"100","unit_rounding_actual":"100","manager":{"id":13,"unique_id":"bTSVzA4e1b","name":null,"username":"\u5409\u7530 \u7ffc","email":"murayama.ryosuke@example.com","unique_id_search_flag":1,"username_search_flag":1,"created_at":{"date":"2019-03-02 15:26:06.000000","timezone_type":3,"timezone":"UTC"},"updated_at":{"date":"2019-03-02 15:26:06.000000","timezone_type":3,"timezone":"UTC"},"deleted_at":null},"users":[{"id":7,"unique_id":"CORWNToj6v","name":null,"username":"\u30c6\u30b9\u30c8\u592a\u90ce","email":"testuser@example.com","unique_id_search_flag":1,"username_search_flag":1,"join_status":"wait","paid":0,"plus_minus":null,"attribute_name":null,"budget":null,"budget_actual":null,"created_at":{"date":"2019-03-02 15:26:06.000000","timezone_type":3,"timezone":"UTC"},"updated_at":{"date":"2019-03-02 15:26:28.000000","timezone_type":3,"timezone":"UTC"},"deleted_at":null},{"id":12,"unique_id":"K5fuAg9Wud","name":null,"username":"\u9234\u6728 \u4e03\u590f","email":"momoko58@example.com","unique_id_search_flag":1,"username_search_flag":1,"join_status":"wait","paid":0,"plus_minus":null,"attribute_name":null,"budget":null,"budget_actual":null,"created_at":{"date":"2019-03-02 15:26:06.000000","timezone_type":3,"timezone":"UTC"},"updated_at":{"date":"2019-03-02 15:26:06.000000","timezone_type":3,"timezone":"UTC"},"deleted_at":null},{"id":15,"unique_id":"7U2vUA0YvN","name":null,"username":"\u4f0a\u85e4 \u7d50\u8863","email":"juno@example.org","unique_id_search_flag":1,"username_search_flag":1,"join_status":"allow","paid":1,"plus_minus":null,"attribute_name":null,"budget":null,"budget_actual":null,"created_at":{"date":"2019-03-02 15:26:06.000000","timezone_type":3,"timezone":"UTC"},"updated_at":{"date":"2019-03-02 15:26:06.000000","timezone_type":3,"timezone":"UTC"},"deleted_at":null},{"id":23,"unique_id":"jFW6MAPaHw","name":null,"username":"\u6728\u6751 \u3042\u3059\u304b","email":"ryosuke20@example.org","unique_id_search_flag":1,"username_search_flag":1,"join_status":"deny","paid":0,"plus_minus":null,"attribute_name":null,"budget":null,"budget_actual":null,"created_at":{"date":"2019-03-02 15:26:06.000000","timezone_type":3,"timezone":"UTC"},"updated_at":{"date":"2019-03-02 15:26:06.000000","timezone_type":3,"timezone":"UTC"},"deleted_at":null},{"id":31,"unique_id":"Xk5awqONnv","name":null,"username":"\u6d25\u7530 \u77e5\u5b9f","email":"aota.rika@example.com","unique_id_search_flag":1,"username_search_flag":1,"join_status":"allow","paid":0,"plus_minus":null,"attribute_name":null,"budget":null,"budget_actual":null,"created_at":{"date":"2019-03-02 15:26:06.000000","timezone_type":3,"timezone":"UTC"},"updated_at":{"date":"2019-03-02 15:26:06.000000","timezone_type":3,"timezone":"UTC"},"deleted_at":null},{"id":39,"unique_id":"I49iMbtdnq","name":null,"username":"\u5c71\u672c \u967d\u5b50","email":"anagisa@example.org","unique_id_search_flag":1,"username_search_flag":1,"join_status":"allow","paid":0,"plus_minus":null,"attribute_name":null,"budget":null,"budget_actual":null,"created_at":{"date":"2019-03-02 15:26:06.000000","timezone_type":3,"timezone":"UTC"},"updated_at":{"date":"2019-03-02 15:26:06.000000","timezone_type":3,"timezone":"UTC"},"deleted_at":null},{"id":48,"unique_id":"CSJXfGzx4w","name":null,"username":"\u30c6\u30b9\u30c8\u30e6\u30fc\u30b6\u30fc\uff12","email":"testuser48@example.com","unique_id_search_flag":1,"username_search_flag":1,"join_status":"deny","paid":0,"plus_minus":null,"attribute_name":null,"budget":null,"budget_actual":null,"created_at":{"date":"2019-03-02 15:26:06.000000","timezone_type":3,"timezone":"UTC"},"updated_at":{"date":"2019-03-02 15:26:28.000000","timezone_type":3,"timezone":"UTC"},"deleted_at":null},{"id":50,"unique_id":"XqkDwOOAwI","name":null,"username":"\u30c6\u30b9\u30c8\u30e6\u30fc\u30b6\u30fc\uff13","email":"testuser50@example.com","unique_id_search_flag":1,"username_search_flag":1,"join_status":"deny","paid":0,"plus_minus":null,"attribute_name":null,"budget":null,"budget_actual":null,"created_at":{"date":"2019-03-02 15:26:06.000000","timezone_type":3,"timezone":"UTC"},"updated_at":{"date":"2019-03-02 15:26:28.000000","timezone_type":3,"timezone":"UTC"},"deleted_at":null}],"created_at":{"date":"2019-03-02 15:26:09.000000","timezone_type":3,"timezone":"UTC"},"updated_at":{"date":"2019-03-02 15:26:09.000000","timezone_type":3,"timezone":"UTC"},"deleted_at":null},{"id":29,"name":"non","shop_id":"J000753015","budget":3079,"actual":8159,"start_time":null,"end_time":null,"unit_rounding_budget":"100","unit_rounding_actual":"100","manager":{"id":13,"unique_id":"bTSVzA4e1b","name":null,"username":"\u5409\u7530 \u7ffc","email":"murayama.ryosuke@example.com","unique_id_search_flag":1,"username_search_flag":1,"created_at":{"date":"2019-03-02 15:26:06.000000","timezone_type":3,"timezone":"UTC"},"updated_at":{"date":"2019-03-02 15:26:06.000000","timezone_type":3,"timezone":"UTC"},"deleted_at":null},"users":[{"id":7,"unique_id":"CORWNToj6v","name":null,"username":"\u30c6\u30b9\u30c8\u592a\u90ce","email":"testuser@example.com","unique_id_search_flag":1,"username_search_flag":1,"join_status":"deny","paid":0,"plus_minus":null,"attribute_name":null,"budget":null,"budget_actual":null,"created_at":{"date":"2019-03-02 15:26:06.000000","timezone_type":3,"timezone":"UTC"},"updated_at":{"date":"2019-03-02 15:26:28.000000","timezone_type":3,"timezone":"UTC"},"deleted_at":null},{"id":8,"unique_id":"YQctNEoTyq","name":null,"username":"\u5409\u672c \u3055\u3086\u308a","email":"akira.yoshida@example.org","unique_id_search_flag":1,"username_search_flag":1,"join_status":"deny","paid":0,"plus_minus":null,"attribute_name":null,"budget":null,"budget_actual":null,"created_at":{"date":"2019-03-02 15:26:06.000000","timezone_type":3,"timezone":"UTC"},"updated_at":{"date":"2019-03-02 15:26:06.000000","timezone_type":3,"timezone":"UTC"},"deleted_at":null},{"id":10,"unique_id":"yJNY6mhW5M","name":null,"username":"\u52a0\u85e4 \u660e\u7f8e","email":"ito.manabu@example.org","unique_id_search_flag":1,"username_search_flag":1,"join_status":"wait","paid":0,"plus_minus":null,"attribute_name":null,"budget":null,"budget_actual":null,"created_at":{"date":"2019-03-02 15:26:06.000000","timezone_type":3,"timezone":"UTC"},"updated_at":{"date":"2019-03-02 15:26:06.000000","timezone_type":3,"timezone":"UTC"},"deleted_at":null},{"id":23,"unique_id":"jFW6MAPaHw","name":null,"username":"\u6728\u6751 \u3042\u3059\u304b","email":"ryosuke20@example.org","unique_id_search_flag":1,"username_search_flag":1,"join_status":"allow","paid":0,"plus_minus":null,"attribute_name":null,"budget":null,"budget_actual":null,"created_at":{"date":"2019-03-02 15:26:06.000000","timezone_type":3,"timezone":"UTC"},"updated_at":{"date":"2019-03-02 15:26:06.000000","timezone_type":3,"timezone":"UTC"},"deleted_at":null},{"id":27,"unique_id":"0ZmdL4KrQB","name":null,"username":"\u6728\u6751 \u6d69","email":"mitsuru.suzuki@example.com","unique_id_search_flag":1,"username_search_flag":1,"join_status":"wait","paid":0,"plus_minus":null,"attribute_name":null,"budget":null,"budget_actual":null,"created_at":{"date":"2019-03-02 15:26:06.000000","timezone_type":3,"timezone":"UTC"},"updated_at":{"date":"2019-03-02 15:26:06.000000","timezone_type":3,"timezone":"UTC"},"deleted_at":null},{"id":46,"unique_id":"th59RZVqKd","name":null,"username":"\u5409\u7530 \u4e03\u590f","email":"uno.kyosuke@example.org","unique_id_search_flag":1,"username_search_flag":1,"join_status":"allow","paid":0,"plus_minus":null,"attribute_name":null,"budget":null,"budget_actual":null,"created_at":{"date":"2019-03-02 15:26:06.000000","timezone_type":3,"timezone":"UTC"},"updated_at":{"date":"2019-03-02 15:26:06.000000","timezone_type":3,"timezone":"UTC"},"deleted_at":null},{"id":48,"unique_id":"CSJXfGzx4w","name":null,"username":"\u30c6\u30b9\u30c8\u30e6\u30fc\u30b6\u30fc\uff12","email":"testuser48@example.com","unique_id_search_flag":1,"username_search_flag":1,"join_status":"wait","paid":0,"plus_minus":null,"attribute_name":null,"budget":null,"budget_actual":null,"created_at":{"date":"2019-03-02 15:26:06.000000","timezone_type":3,"timezone":"UTC"},"updated_at":{"date":"2019-03-02 15:26:28.000000","timezone_type":3,"timezone":"UTC"},"deleted_at":null},{"id":50,"unique_id":"XqkDwOOAwI","name":null,"username":"\u30c6\u30b9\u30c8\u30e6\u30fc\u30b6\u30fc\uff13","email":"testuser50@example.com","unique_id_search_flag":1,"username_search_flag":1,"join_status":"wait","paid":0,"plus_minus":null,"attribute_name":null,"budget":null,"budget_actual":null,"created_at":{"date":"2019-03-02 15:26:06.000000","timezone_type":3,"timezone":"UTC"},"updated_at":{"date":"2019-03-02 15:26:28.000000","timezone_type":3,"timezone":"UTC"},"deleted_at":null}],"created_at":{"date":"2019-03-02 15:26:09.000000","timezone_type":3,"timezone":"UTC"},"updated_at":{"date":"2019-03-02 15:26:09.000000","timezone_type":3,"timezone":"UTC"},"deleted_at":null},{"id":54,"name":"eligendi","shop_id":"J001177654","budget":24473,"actual":40210,"start_time":"2019-02-25 15:26:13","end_time":"2019-03-12 15:26:13","unit_rounding_budget":"100","unit_rounding_actual":"100","manager":{"id":20,"unique_id":"eGwHjPernR","name":null,"username":"\u91ce\u6751 \u76f4\u4eba","email":"takuma.saito@example.net","unique_id_search_flag":1,"username_search_flag":1,"created_at":{"date":"2019-03-02 15:26:06.000000","timezone_type":3,"timezone":"UTC"},"updated_at":{"date":"2019-03-02 15:26:06.000000","timezone_type":3,"timezone":"UTC"},"deleted_at":null},"users":[{"id":7,"unique_id":"CORWNToj6v","name":null,"username":"\u30c6\u30b9\u30c8\u592a\u90ce","email":"testuser@example.com","unique_id_search_flag":1,"username_search_flag":1,"join_status":"deny","paid":0,"plus_minus":null,"attribute_name":null,"budget":null,"budget_actual":null,"created_at":{"date":"2019-03-02 15:26:06.000000","timezone_type":3,"timezone":"UTC"},"updated_at":{"date":"2019-03-02 15:26:28.000000","timezone_type":3,"timezone":"UTC"},"deleted_at":null},{"id":8,"unique_id":"YQctNEoTyq","name":null,"username":"\u5409\u672c \u3055\u3086\u308a","email":"akira.yoshida@example.org","unique_id_search_flag":1,"username_search_flag":1,"join_status":"wait","paid":0,"plus_minus":null,"attribute_name":null,"budget":null,"budget_actual":null,"created_at":{"date":"2019-03-02 15:26:06.000000","timezone_type":3,"timezone":"UTC"},"updated_at":{"date":"2019-03-02 15:26:06.000000","timezone_type":3,"timezone":"UTC"},"deleted_at":null},{"id":26,"unique_id":"ocbTn0ylwc","name":null,"username":"\u6850\u5c71 \u967d\u4e00","email":"pnakamura@example.net","unique_id_search_flag":1,"username_search_flag":1,"join_status":"allow","paid":0,"plus_minus":null,"attribute_name":null,"budget":null,"budget_actual":null,"created_at":{"date":"2019-03-02 15:26:06.000000","timezone_type":3,"timezone":"UTC"},"updated_at":{"date":"2019-03-02 15:26:06.000000","timezone_type":3,"timezone":"UTC"},"deleted_at":null},{"id":28,"unique_id":"zsVDfRCOya","name":null,"username":"\u52a0\u85e4 \u4eac\u52a9","email":"kudo.mitsuru@example.net","unique_id_search_flag":1,"username_search_flag":1,"join_status":"allow","paid":0,"plus_minus":null,"attribute_name":null,"budget":null,"budget_actual":null,"created_at":{"date":"2019-03-02 15:26:06.000000","timezone_type":3,"timezone":"UTC"},"updated_at":{"date":"2019-03-02 15:26:06.000000","timezone_type":3,"timezone":"UTC"},"deleted_at":null},{"id":42,"unique_id":"WZvU6cXXOp","name":null,"username":"\u539f\u7530 \u821e","email":"taro.suzuki@example.com","unique_id_search_flag":1,"username_search_flag":1,"join_status":"allow","paid":0,"plus_minus":null,"attribute_name":null,"budget":null,"budget_actual":null,"created_at":{"date":"2019-03-02 15:26:06.000000","timezone_type":3,"timezone":"UTC"},"updated_at":{"date":"2019-03-02 15:26:06.000000","timezone_type":3,"timezone":"UTC"},"deleted_at":null}],"created_at":{"date":"2019-03-02 15:26:13.000000","timezone_type":3,"timezone":"UTC"},"updated_at":{"date":"2019-03-02 15:26:13.000000","timezone_type":3,"timezone":"UTC"},"deleted_at":null},{"id":56,"name":"velit","shop_id":"J000449898","budget":11576,"actual":14741,"start_time":"2019-03-07 15:26:13","end_time":"2019-03-12 15:26:13","unit_rounding_budget":"100","unit_rounding_actual":"100","manager":{"id":20,"unique_id":"eGwHjPernR","name":null,"username":"\u91ce\u6751 \u76f4\u4eba","email":"takuma.saito@example.net","unique_id_search_flag":1,"username_search_flag":1,"created_at":{"date":"2019-03-02 15:26:06.000000","timezone_type":3,"timezone":"UTC"},"updated_at":{"date":"2019-03-02 15:26:06.000000","timezone_type":3,"timezone":"UTC"},"deleted_at":null},"users":[{"id":7,"unique_id":"CORWNToj6v","name":null,"username":"\u30c6\u30b9\u30c8\u592a\u90ce","email":"testuser@example.com","unique_id_search_flag":1,"username_search_flag":1,"join_status":"wait","paid":0,"plus_minus":null,"attribute_name":null,"budget":null,"budget_actual":null,"created_at":{"date":"2019-03-02 15:26:06.000000","timezone_type":3,"timezone":"UTC"},"updated_at":{"date":"2019-03-02 15:26:28.000000","timezone_type":3,"timezone":"UTC"},"deleted_at":null},{"id":21,"unique_id":"lSwgexhJGN","name":null,"username":"\u5de5\u85e4 \u76f4\u5b50","email":"enakajima@example.org","unique_id_search_flag":1,"username_search_flag":1,"join_status":"deny","paid":0,"plus_minus":null,"attribute_name":null,"budget":null,"budget_actual":null,"created_at":{"date":"2019-03-02 15:26:06.000000","timezone_type":3,"timezone":"UTC"},"updated_at":{"date":"2019-03-02 15:26:06.000000","timezone_type":3,"timezone":"UTC"},"deleted_at":null},{"id":25,"unique_id":"iogytFIaLq","name":null,"username":"\u4f50\u3005\u6728 \u4fee\u5e73","email":"yui60@example.org","unique_id_search_flag":1,"username_search_flag":1,"join_status":"allow","paid":0,"plus_minus":null,"attribute_name":null,"budget":null,"budget_actual":null,"created_at":{"date":"2019-03-02 15:26:06.000000","timezone_type":3,"timezone":"UTC"},"updated_at":{"date":"2019-03-02 15:26:06.000000","timezone_type":3,"timezone":"UTC"},"deleted_at":null},{"id":26,"unique_id":"ocbTn0ylwc","name":null,"username":"\u6850\u5c71 \u967d\u4e00","email":"pnakamura@example.net","unique_id_search_flag":1,"username_search_flag":1,"join_status":"wait","paid":0,"plus_minus":null,"attribute_name":null,"budget":null,"budget_actual":null,"created_at":{"date":"2019-03-02 15:26:06.000000","timezone_type":3,"timezone":"UTC"},"updated_at":{"date":"2019-03-02 15:26:06.000000","timezone_type":3,"timezone":"UTC"},"deleted_at":null},{"id":47,"unique_id":"FwHeEEyOFe","name":null,"username":"\u5bae\u6ca2 \u52a0\u5948","email":"satomi25@example.net","unique_id_search_flag":1,"username_search_flag":1,"join_status":"allow","paid":0,"plus_minus":null,"attribute_name":null,"budget":null,"budget_actual":null,"created_at":{"date":"2019-03-02 15:26:06.000000","timezone_type":3,"timezone":"UTC"},"updated_at":{"date":"2019-03-02 15:26:06.000000","timezone_type":3,"timezone":"UTC"},"deleted_at":null}],"created_at":{"date":"2019-03-02 15:26:13.000000","timezone_type":3,"timezone":"UTC"},"updated_at":{"date":"2019-03-02 15:26:13.000000","timezone_type":3,"timezone":"UTC"},"deleted_at":null},{"id":71,"name":"ipsam","shop_id":"J001182216","budget":12564,"actual":28562,"start_time":"2019-02-25 15:26:15","end_time":"2019-03-12 15:26:15","unit_rounding_budget":"100","unit_rounding_actual":"100","manager":{"id":24,"unique_id":"LCODgB7rzh","name":null,"username":"\u77f3\u7530 \u88d5\u7f8e\u5b50","email":"xwatanabe@example.org","unique_id_search_flag":1,"username_search_flag":1,"created_at":{"date":"2019-03-02 15:26:06.000000","timezone_type":3,"timezone":"UTC"},"updated_at":{"date":"2019-03-02 15:26:06.000000","timezone_type":3,"timezone":"UTC"},"deleted_at":null},"users":[{"id":7,"unique_id":"CORWNToj6v","name":null,"username":"\u30c6\u30b9\u30c8\u592a\u90ce","email":"testuser@example.com","unique_id_search_flag":1,"username_search_flag":1,"join_status":"allow","paid":1,"plus_minus":null,"attribute_name":null,"budget":null,"budget_actual":null,"created_at":{"date":"2019-03-02 15:26:06.000000","timezone_type":3,"timezone":"UTC"},"updated_at":{"date":"2019-03-02 15:26:28.000000","timezone_type":3,"timezone":"UTC"},"deleted_at":null},{"id":10,"unique_id":"yJNY6mhW5M","name":null,"username":"\u52a0\u85e4 \u660e\u7f8e","email":"ito.manabu@example.org","unique_id_search_flag":1,"username_search_flag":1,"join_status":"deny","paid":0,"plus_minus":null,"attribute_name":null,"budget":null,"budget_actual":null,"created_at":{"date":"2019-03-02 15:26:06.000000","timezone_type":3,"timezone":"UTC"},"updated_at":{"date":"2019-03-02 15:26:06.000000","timezone_type":3,"timezone":"UTC"},"deleted_at":null},{"id":17,"unique_id":"0zEcDc0oVd","name":null,"username":"\u6d25\u7530 \u7d50\u8863","email":"hideki.kobayashi@example.org","unique_id_search_flag":1,"username_search_flag":1,"join_status":"allow","paid":0,"plus_minus":null,"attribute_name":null,"budget":null,"budget_actual":null,"created_at":{"date":"2019-03-02 15:26:06.000000","timezone_type":3,"timezone":"UTC"},"updated_at":{"date":"2019-03-02 15:26:06.000000","timezone_type":3,"timezone":"UTC"},"deleted_at":null},{"id":21,"unique_id":"lSwgexhJGN","name":null,"username":"\u5de5\u85e4 \u76f4\u5b50","email":"enakajima@example.org","unique_id_search_flag":1,"username_search_flag":1,"join_status":"allow","paid":1,"plus_minus":null,"attribute_name":null,"budget":null,"budget_actual":null,"created_at":{"date":"2019-03-02 15:26:06.000000","timezone_type":3,"timezone":"UTC"},"updated_at":{"date":"2019-03-02 15:26:06.000000","timezone_type":3,"timezone":"UTC"},"deleted_at":null},{"id":37,"unique_id":"ESiubQLqJh","name":null,"username":"\u6d5c\u7530 \u7fd4\u592a","email":"mitsuru.harada@example.com","unique_id_search_flag":1,"username_search_flag":1,"join_status":"deny","paid":0,"plus_minus":null,"attribute_name":null,"budget":null,"budget_actual":null,"created_at":{"date":"2019-03-02 15:26:06.000000","timezone_type":3,"timezone":"UTC"},"updated_at":{"date":"2019-03-02 15:26:06.000000","timezone_type":3,"timezone":"UTC"},"deleted_at":null},{"id":42,"unique_id":"WZvU6cXXOp","name":null,"username":"\u539f\u7530 \u821e","email":"taro.suzuki@example.com","unique_id_search_flag":1,"username_search_flag":1,"join_status":"wait","paid":0,"plus_minus":null,"attribute_name":null,"budget":null,"budget_actual":null,"created_at":{"date":"2019-03-02 15:26:06.000000","timezone_type":3,"timezone":"UTC"},"updated_at":{"date":"2019-03-02 15:26:06.000000","timezone_type":3,"timezone":"UTC"},"deleted_at":null},{"id":46,"unique_id":"th59RZVqKd","name":null,"username":"\u5409\u7530 \u4e03\u590f","email":"uno.kyosuke@example.org","unique_id_search_flag":1,"username_search_flag":1,"join_status":"allow","paid":1,"plus_minus":null,"attribute_name":null,"budget":null,"budget_actual":null,"created_at":{"date":"2019-03-02 15:26:06.000000","timezone_type":3,"timezone":"UTC"},"updated_at":{"date":"2019-03-02 15:26:06.000000","timezone_type":3,"timezone":"UTC"},"deleted_at":null}],"created_at":{"date":"2019-03-02 15:26:15.000000","timezone_type":3,"timezone":"UTC"},"updated_at":{"date":"2019-03-02 15:26:15.000000","timezone_type":3,"timezone":"UTC"},"deleted_at":null},{"id":74,"name":"sed","shop_id":"J000109445","budget":20918,"actual":34838,"start_time":"2019-02-20 15:26:15","end_time":"2019-02-25 15:26:15","unit_rounding_budget":"100","unit_rounding_actual":"100","manager":{"id":25,"unique_id":"iogytFIaLq","name":null,"username":"\u4f50\u3005\u6728 \u4fee\u5e73","email":"yui60@example.org","unique_id_search_flag":1,"username_search_flag":1,"created_at":{"date":"2019-03-02 15:26:06.000000","timezone_type":3,"timezone":"UTC"},"updated_at":{"date":"2019-03-02 15:26:06.000000","timezone_type":3,"timezone":"UTC"},"deleted_at":null},"users":[{"id":7,"unique_id":"CORWNToj6v","name":null,"username":"\u30c6\u30b9\u30c8\u592a\u90ce","email":"testuser@example.com","unique_id_search_flag":1,"username_search_flag":1,"join_status":"allow","paid":1,"plus_minus":null,"attribute_name":null,"budget":null,"budget_actual":null,"created_at":{"date":"2019-03-02 15:26:06.000000","timezone_type":3,"timezone":"UTC"},"updated_at":{"date":"2019-03-02 15:26:28.000000","timezone_type":3,"timezone":"UTC"},"deleted_at":null},{"id":11,"unique_id":"iIzTTmcOl0","name":null,"username":"\u5c71\u7530 \u660e\u7f8e","email":"ryohei47@example.com","unique_id_search_flag":1,"username_search_flag":1,"join_status":"wait","paid":0,"plus_minus":null,"attribute_name":null,"budget":null,"budget_actual":null,"created_at":{"date":"2019-03-02 15:26:06.000000","timezone_type":3,"timezone":"UTC"},"updated_at":{"date":"2019-03-02 15:26:06.000000","timezone_type":3,"timezone":"UTC"},"deleted_at":null},{"id":17,"unique_id":"0zEcDc0oVd","name":null,"username":"\u6d25\u7530 \u7d50\u8863","email":"hideki.kobayashi@example.org","unique_id_search_flag":1,"username_search_flag":1,"join_status":"wait","paid":0,"plus_minus":null,"attribute_name":null,"budget":null,"budget_actual":null,"created_at":{"date":"2019-03-02 15:26:06.000000","timezone_type":3,"timezone":"UTC"},"updated_at":{"date":"2019-03-02 15:26:06.000000","timezone_type":3,"timezone":"UTC"},"deleted_at":null},{"id":22,"unique_id":"TXrm4a22Dk","name":null,"username":"\u5c0f\u6cc9 \u88d5\u7f8e\u5b50","email":"xfujimoto@example.net","unique_id_search_flag":1,"username_search_flag":1,"join_status":"wait","paid":0,"plus_minus":null,"attribute_name":null,"budget":null,"budget_actual":null,"created_at":{"date":"2019-03-02 15:26:06.000000","timezone_type":3,"timezone":"UTC"},"updated_at":{"date":"2019-03-02 15:26:06.000000","timezone_type":3,"timezone":"UTC"},"deleted_at":null},{"id":23,"unique_id":"jFW6MAPaHw","name":null,"username":"\u6728\u6751 \u3042\u3059\u304b","email":"ryosuke20@example.org","unique_id_search_flag":1,"username_search_flag":1,"join_status":"wait","paid":0,"plus_minus":null,"attribute_name":null,"budget":null,"budget_actual":null,"created_at":{"date":"2019-03-02 15:26:06.000000","timezone_type":3,"timezone":"UTC"},"updated_at":{"date":"2019-03-02 15:26:06.000000","timezone_type":3,"timezone":"UTC"},"deleted_at":null},{"id":34,"unique_id":"qfzTe7qR6n","name":null,"username":"\u5c71\u672c \u5b66","email":"atakahashi@example.org","unique_id_search_flag":1,"username_search_flag":1,"join_status":"wait","paid":0,"plus_minus":null,"attribute_name":null,"budget":null,"budget_actual":null,"created_at":{"date":"2019-03-02 15:26:06.000000","timezone_type":3,"timezone":"UTC"},"updated_at":{"date":"2019-03-02 15:26:06.000000","timezone_type":3,"timezone":"UTC"},"deleted_at":null},{"id":42,"unique_id":"WZvU6cXXOp","name":null,"username":"\u539f\u7530 \u821e","email":"taro.suzuki@example.com","unique_id_search_flag":1,"username_search_flag":1,"join_status":"wait","paid":0,"plus_minus":null,"attribute_name":null,"budget":null,"budget_actual":null,"created_at":{"date":"2019-03-02 15:26:06.000000","timezone_type":3,"timezone":"UTC"},"updated_at":{"date":"2019-03-02 15:26:06.000000","timezone_type":3,"timezone":"UTC"},"deleted_at":null},{"id":45,"unique_id":"WqZoj7f9dl","name":null,"username":"\u5409\u672c \u5e79","email":"yamagishi.osamu@example.net","unique_id_search_flag":1,"username_search_flag":1,"join_status":"deny","paid":0,"plus_minus":null,"attribute_name":null,"budget":null,"budget_actual":null,"created_at":{"date":"2019-03-02 15:26:06.000000","timezone_type":3,"timezone":"UTC"},"updated_at":{"date":"2019-03-02 15:26:06.000000","timezone_type":3,"timezone":"UTC"},"deleted_at":null}],"created_at":{"date":"2019-03-02 15:26:15.000000","timezone_type":3,"timezone":"UTC"},"updated_at":{"date":"2019-03-02 15:26:15.000000","timezone_type":3,"timezone":"UTC"},"deleted_at":null},{"id":76,"name":"molestiae","shop_id":"J001178400","budget":28024,"actual":48753,"start_time":"2019-02-20 15:26:15","end_time":"2019-02-25 15:26:15","unit_rounding_budget":"100","unit_rounding_actual":"100","manager":{"id":25,"unique_id":"iogytFIaLq","name":null,"username":"\u4f50\u3005\u6728 \u4fee\u5e73","email":"yui60@example.org","unique_id_search_flag":1,"username_search_flag":1,"created_at":{"date":"2019-03-02 15:26:06.000000","timezone_type":3,"timezone":"UTC"},"updated_at":{"date":"2019-03-02 15:26:06.000000","timezone_type":3,"timezone":"UTC"},"deleted_at":null},"users":[{"id":7,"unique_id":"CORWNToj6v","name":null,"username":"\u30c6\u30b9\u30c8\u592a\u90ce","email":"testuser@example.com","unique_id_search_flag":1,"username_search_flag":1,"join_status":"allow","paid":0,"plus_minus":null,"attribute_name":null,"budget":null,"budget_actual":null,"created_at":{"date":"2019-03-02 15:26:06.000000","timezone_type":3,"timezone":"UTC"},"updated_at":{"date":"2019-03-02 15:26:28.000000","timezone_type":3,"timezone":"UTC"},"deleted_at":null},{"id":11,"unique_id":"iIzTTmcOl0","name":null,"username":"\u5c71\u7530 \u660e\u7f8e","email":"ryohei47@example.com","unique_id_search_flag":1,"username_search_flag":1,"join_status":"deny","paid":0,"plus_minus":null,"attribute_name":null,"budget":null,"budget_actual":null,"created_at":{"date":"2019-03-02 15:26:06.000000","timezone_type":3,"timezone":"UTC"},"updated_at":{"date":"2019-03-02 15:26:06.000000","timezone_type":3,"timezone":"UTC"},"deleted_at":null},{"id":18,"unique_id":"nMImrHLsCM","name":null,"username":"\u4e09\u5b85 \u592a\u90ce","email":"kijima.yasuhiro@example.com","unique_id_search_flag":1,"username_search_flag":1,"join_status":"deny","paid":0,"plus_minus":null,"attribute_name":null,"budget":null,"budget_actual":null,"created_at":{"date":"2019-03-02 15:26:06.000000","timezone_type":3,"timezone":"UTC"},"updated_at":{"date":"2019-03-02 15:26:06.000000","timezone_type":3,"timezone":"UTC"},"deleted_at":null},{"id":22,"unique_id":"TXrm4a22Dk","name":null,"username":"\u5c0f\u6cc9 \u88d5\u7f8e\u5b50","email":"xfujimoto@example.net","unique_id_search_flag":1,"username_search_flag":1,"join_status":"wait","paid":0,"plus_minus":null,"attribute_name":null,"budget":null,"budget_actual":null,"created_at":{"date":"2019-03-02 15:26:06.000000","timezone_type":3,"timezone":"UTC"},"updated_at":{"date":"2019-03-02 15:26:06.000000","timezone_type":3,"timezone":"UTC"},"deleted_at":null},{"id":23,"unique_id":"jFW6MAPaHw","name":null,"username":"\u6728\u6751 \u3042\u3059\u304b","email":"ryosuke20@example.org","unique_id_search_flag":1,"username_search_flag":1,"join_status":"deny","paid":0,"plus_minus":null,"attribute_name":null,"budget":null,"budget_actual":null,"created_at":{"date":"2019-03-02 15:26:06.000000","timezone_type":3,"timezone":"UTC"},"updated_at":{"date":"2019-03-02 15:26:06.000000","timezone_type":3,"timezone":"UTC"},"deleted_at":null},{"id":26,"unique_id":"ocbTn0ylwc","name":null,"username":"\u6850\u5c71 \u967d\u4e00","email":"pnakamura@example.net","unique_id_search_flag":1,"username_search_flag":1,"join_status":"wait","paid":0,"plus_minus":null,"attribute_name":null,"budget":null,"budget_actual":null,"created_at":{"date":"2019-03-02 15:26:06.000000","timezone_type":3,"timezone":"UTC"},"updated_at":{"date":"2019-03-02 15:26:06.000000","timezone_type":3,"timezone":"UTC"},"deleted_at":null},{"id":42,"unique_id":"WZvU6cXXOp","name":null,"username":"\u539f\u7530 \u821e","email":"taro.suzuki@example.com","unique_id_search_flag":1,"username_search_flag":1,"join_status":"deny","paid":0,"plus_minus":null,"attribute_name":null,"budget":null,"budget_actual":null,"created_at":{"date":"2019-03-02 15:26:06.000000","timezone_type":3,"timezone":"UTC"},"updated_at":{"date":"2019-03-02 15:26:06.000000","timezone_type":3,"timezone":"UTC"},"deleted_at":null},{"id":44,"unique_id":"ZF5evtBrPn","name":null,"username":"\u52a0\u85e4 \u9999\u7e54","email":"yamamoto.satomi@example.com","unique_id_search_flag":1,"username_search_flag":1,"join_status":"allow","paid":0,"plus_minus":null,"attribute_name":null,"budget":null,"budget_actual":null,"created_at":{"date":"2019-03-02 15:26:06.000000","timezone_type":3,"timezone":"UTC"},"updated_at":{"date":"2019-03-02 15:26:06.000000","timezone_type":3,"timezone":"UTC"},"deleted_at":null}],"created_at":{"date":"2019-03-02 15:26:15.000000","timezone_type":3,"timezone":"UTC"},"updated_at":{"date":"2019-03-02 15:26:15.000000","timezone_type":3,"timezone":"UTC"},"deleted_at":null},{"id":79,"name":"quia","shop_id":"J001178400","budget":3608,"actual":8040,"start_time":"2019-02-20 15:26:16","end_time":"2019-02-25 15:26:16","unit_rounding_budget":"100","unit_rounding_actual":"100","manager":{"id":26,"unique_id":"ocbTn0ylwc","name":null,"username":"\u6850\u5c71 \u967d\u4e00","email":"pnakamura@example.net","unique_id_search_flag":1,"username_search_flag":1,"created_at":{"date":"2019-03-02 15:26:06.000000","timezone_type":3,"timezone":"UTC"},"updated_at":{"date":"2019-03-02 15:26:06.000000","timezone_type":3,"timezone":"UTC"},"deleted_at":null},"users":[{"id":7,"unique_id":"CORWNToj6v","name":null,"username":"\u30c6\u30b9\u30c8\u592a\u90ce","email":"testuser@example.com","unique_id_search_flag":1,"username_search_flag":1,"join_status":"allow","paid":0,"plus_minus":null,"attribute_name":null,"budget":null,"budget_actual":null,"created_at":{"date":"2019-03-02 15:26:06.000000","timezone_type":3,"timezone":"UTC"},"updated_at":{"date":"2019-03-02 15:26:28.000000","timezone_type":3,"timezone":"UTC"},"deleted_at":null},{"id":14,"unique_id":"NUUq5pi71A","name":null,"username":"\u5c71\u53e3 \u88d5\u6a39","email":"watanabe.rika@example.org","unique_id_search_flag":1,"username_search_flag":1,"join_status":"allow","paid":1,"plus_minus":null,"attribute_name":null,"budget":null,"budget_actual":null,"created_at":{"date":"2019-03-02 15:26:06.000000","timezone_type":3,"timezone":"UTC"},"updated_at":{"date":"2019-03-02 15:26:06.000000","timezone_type":3,"timezone":"UTC"},"deleted_at":null},{"id":20,"unique_id":"eGwHjPernR","name":null,"username":"\u91ce\u6751 \u76f4\u4eba","email":"takuma.saito@example.net","unique_id_search_flag":1,"username_search_flag":1,"join_status":"deny","paid":0,"plus_minus":null,"attribute_name":null,"budget":null,"budget_actual":null,"created_at":{"date":"2019-03-02 15:26:06.000000","timezone_type":3,"timezone":"UTC"},"updated_at":{"date":"2019-03-02 15:26:06.000000","timezone_type":3,"timezone":"UTC"},"deleted_at":null},{"id":22,"unique_id":"TXrm4a22Dk","name":null,"username":"\u5c0f\u6cc9 \u88d5\u7f8e\u5b50","email":"xfujimoto@example.net","unique_id_search_flag":1,"username_search_flag":1,"join_status":"allow","paid":1,"plus_minus":null,"attribute_name":null,"budget":null,"budget_actual":null,"created_at":{"date":"2019-03-02 15:26:06.000000","timezone_type":3,"timezone":"UTC"},"updated_at":{"date":"2019-03-02 15:26:06.000000","timezone_type":3,"timezone":"UTC"},"deleted_at":null},{"id":27,"unique_id":"0ZmdL4KrQB","name":null,"username":"\u6728\u6751 \u6d69","email":"mitsuru.suzuki@example.com","unique_id_search_flag":1,"username_search_flag":1,"join_status":"deny","paid":0,"plus_minus":null,"attribute_name":null,"budget":null,"budget_actual":null,"created_at":{"date":"2019-03-02 15:26:06.000000","timezone_type":3,"timezone":"UTC"},"updated_at":{"date":"2019-03-02 15:26:06.000000","timezone_type":3,"timezone":"UTC"},"deleted_at":null},{"id":38,"unique_id":"VUUITRnJwp","name":null,"username":"\u4e95\u4e0a \u304f\u307f\u5b50","email":"chiyo16@example.net","unique_id_search_flag":1,"username_search_flag":1,"join_status":"deny","paid":0,"plus_minus":null,"attribute_name":null,"budget":null,"budget_actual":null,"created_at":{"date":"2019-03-02 15:26:06.000000","timezone_type":3,"timezone":"UTC"},"updated_at":{"date":"2019-03-02 15:26:06.000000","timezone_type":3,"timezone":"UTC"},"deleted_at":null},{"id":49,"unique_id":"ioRicFKyK1","name":null,"username":"\u30c6\u30b9\u30c8\u30e6\u30fc\u30b6\u30fc\uff12","email":"testuser49@example.com","unique_id_search_flag":1,"username_search_flag":1,"join_status":"wait","paid":0,"plus_minus":null,"attribute_name":null,"budget":null,"budget_actual":null,"created_at":{"date":"2019-03-02 15:26:06.000000","timezone_type":3,"timezone":"UTC"},"updated_at":{"date":"2019-03-02 15:26:28.000000","timezone_type":3,"timezone":"UTC"},"deleted_at":null}],"created_at":{"date":"2019-03-02 15:26:16.000000","timezone_type":3,"timezone":"UTC"},"updated_at":{"date":"2019-03-02 15:26:16.000000","timezone_type":3,"timezone":"UTC"},"deleted_at":null},{"id":80,"name":"non","shop_id":"J001182216","budget":29205,"actual":33139,"start_time":"2019-02-25 15:26:16","end_time":null,"unit_rounding_budget":"100","unit_rounding_actual":"100","manager":{"id":26,"unique_id":"ocbTn0ylwc","name":null,"username":"\u6850\u5c71 \u967d\u4e00","email":"pnakamura@example.net","unique_id_search_flag":1,"username_search_flag":1,"created_at":{"date":"2019-03-02 15:26:06.000000","timezone_type":3,"timezone":"UTC"},"updated_at":{"date":"2019-03-02 15:26:06.000000","timezone_type":3,"timezone":"UTC"},"deleted_at":null},"users":[{"id":7,"unique_id":"CORWNToj6v","name":null,"username":"\u30c6\u30b9\u30c8\u592a\u90ce","email":"testuser@example.com","unique_id_search_flag":1,"username_search_flag":1,"join_status":"wait","paid":0,"plus_minus":null,"attribute_name":null,"budget":null,"budget_actual":null,"created_at":{"date":"2019-03-02 15:26:06.000000","timezone_type":3,"timezone":"UTC"},"updated_at":{"date":"2019-03-02 15:26:28.000000","timezone_type":3,"timezone":"UTC"},"deleted_at":null},{"id":10,"unique_id":"yJNY6mhW5M","name":null,"username":"\u52a0\u85e4 \u660e\u7f8e","email":"ito.manabu@example.org","unique_id_search_flag":1,"username_search_flag":1,"join_status":"wait","paid":0,"plus_minus":null,"attribute_name":null,"budget":null,"budget_actual":null,"created_at":{"date":"2019-03-02 15:26:06.000000","timezone_type":3,"timezone":"UTC"},"updated_at":{"date":"2019-03-02 15:26:06.000000","timezone_type":3,"timezone":"UTC"},"deleted_at":null},{"id":12,"unique_id":"K5fuAg9Wud","name":null,"username":"\u9234\u6728 \u4e03\u590f","email":"momoko58@example.com","unique_id_search_flag":1,"username_search_flag":1,"join_status":"allow","paid":1,"plus_minus":null,"attribute_name":null,"budget":null,"budget_actual":null,"created_at":{"date":"2019-03-02 15:26:06.000000","timezone_type":3,"timezone":"UTC"},"updated_at":{"date":"2019-03-02 15:26:06.000000","timezone_type":3,"timezone":"UTC"},"deleted_at":null},{"id":20,"unique_id":"eGwHjPernR","name":null,"username":"\u91ce\u6751 \u76f4\u4eba","email":"takuma.saito@example.net","unique_id_search_flag":1,"username_search_flag":1,"join_status":"allow","paid":0,"plus_minus":null,"attribute_name":null,"budget":null,"budget_actual":null,"created_at":{"date":"2019-03-02 15:26:06.000000","timezone_type":3,"timezone":"UTC"},"updated_at":{"date":"2019-03-02 15:26:06.000000","timezone_type":3,"timezone":"UTC"},"deleted_at":null},{"id":22,"unique_id":"TXrm4a22Dk","name":null,"username":"\u5c0f\u6cc9 \u88d5\u7f8e\u5b50","email":"xfujimoto@example.net","unique_id_search_flag":1,"username_search_flag":1,"join_status":"deny","paid":0,"plus_minus":null,"attribute_name":null,"budget":null,"budget_actual":null,"created_at":{"date":"2019-03-02 15:26:06.000000","timezone_type":3,"timezone":"UTC"},"updated_at":{"date":"2019-03-02 15:26:06.000000","timezone_type":3,"timezone":"UTC"},"deleted_at":null},{"id":24,"unique_id":"LCODgB7rzh","name":null,"username":"\u77f3\u7530 \u88d5\u7f8e\u5b50","email":"xwatanabe@example.org","unique_id_search_flag":1,"username_search_flag":1,"join_status":"wait","paid":0,"plus_minus":null,"attribute_name":null,"budget":null,"budget_actual":null,"created_at":{"date":"2019-03-02 15:26:06.000000","timezone_type":3,"timezone":"UTC"},"updated_at":{"date":"2019-03-02 15:26:06.000000","timezone_type":3,"timezone":"UTC"},"deleted_at":null},{"id":36,"unique_id":"5ambfGXHHq","name":null,"username":"\u4e09\u5b85 \u771f\u7dbe","email":"kimura.mikako@example.com","unique_id_search_flag":1,"username_search_flag":1,"join_status":"wait","paid":0,"plus_minus":null,"attribute_name":null,"budget":null,"budget_actual":null,"created_at":{"date":"2019-03-02 15:26:06.000000","timezone_type":3,"timezone":"UTC"},"updated_at":{"date":"2019-03-02 15:26:06.000000","timezone_type":3,"timezone":"UTC"},"deleted_at":null}],"created_at":{"date":"2019-03-02 15:26:16.000000","timezone_type":3,"timezone":"UTC"},"updated_at":{"date":"2019-03-02 15:26:16.000000","timezone_type":3,"timezone":"UTC"},"deleted_at":null},{"id":100,"name":"doloribus","shop_id":"J000742418","budget":5427,"actual":24276,"start_time":"2019-02-25 15:26:18","end_time":null,"unit_rounding_budget":"100","unit_rounding_actual":"100","manager":{"id":31,"unique_id":"Xk5awqONnv","name":null,"username":"\u6d25\u7530 \u77e5\u5b9f","email":"aota.rika@example.com","unique_id_search_flag":1,"username_search_flag":1,"created_at":{"date":"2019-03-02 15:26:06.000000","timezone_type":3,"timezone":"UTC"},"updated_at":{"date":"2019-03-02 15:26:06.000000","timezone_type":3,"timezone":"UTC"},"deleted_at":null},"users":[{"id":7,"unique_id":"CORWNToj6v","name":null,"username":"\u30c6\u30b9\u30c8\u592a\u90ce","email":"testuser@example.com","unique_id_search_flag":1,"username_search_flag":1,"join_status":"wait","paid":0,"plus_minus":null,"attribute_name":null,"budget":null,"budget_actual":null,"created_at":{"date":"2019-03-02 15:26:06.000000","timezone_type":3,"timezone":"UTC"},"updated_at":{"date":"2019-03-02 15:26:28.000000","timezone_type":3,"timezone":"UTC"},"deleted_at":null},{"id":29,"unique_id":"6x852vmS95","name":null,"username":"\u6d25\u7530 \u9999\u7e54","email":"uno.momoko@example.com","unique_id_search_flag":1,"username_search_flag":1,"join_status":"allow","paid":0,"plus_minus":null,"attribute_name":null,"budget":null,"budget_actual":null,"created_at":{"date":"2019-03-02 15:26:06.000000","timezone_type":3,"timezone":"UTC"},"updated_at":{"date":"2019-03-02 15:26:06.000000","timezone_type":3,"timezone":"UTC"},"deleted_at":null},{"id":30,"unique_id":"Lat0uC4PeV","name":null,"username":"\u5c71\u7530 \u3055\u3086\u308a","email":"shota.takahashi@example.com","unique_id_search_flag":1,"username_search_flag":1,"join_status":"wait","paid":0,"plus_minus":null,"attribute_name":null,"budget":null,"budget_actual":null,"created_at":{"date":"2019-03-02 15:26:06.000000","timezone_type":3,"timezone":"UTC"},"updated_at":{"date":"2019-03-02 15:26:06.000000","timezone_type":3,"timezone":"UTC"},"deleted_at":null},{"id":37,"unique_id":"ESiubQLqJh","name":null,"username":"\u6d5c\u7530 \u7fd4\u592a","email":"mitsuru.harada@example.com","unique_id_search_flag":1,"username_search_flag":1,"join_status":"allow","paid":1,"plus_minus":null,"attribute_name":null,"budget":null,"budget_actual":null,"created_at":{"date":"2019-03-02 15:26:06.000000","timezone_type":3,"timezone":"UTC"},"updated_at":{"date":"2019-03-02 15:26:06.000000","timezone_type":3,"timezone":"UTC"},"deleted_at":null},{"id":39,"unique_id":"I49iMbtdnq","name":null,"username":"\u5c71\u672c \u967d\u5b50","email":"anagisa@example.org","unique_id_search_flag":1,"username_search_flag":1,"join_status":"wait","paid":0,"plus_minus":null,"attribute_name":null,"budget":null,"budget_actual":null,"created_at":{"date":"2019-03-02 15:26:06.000000","timezone_type":3,"timezone":"UTC"},"updated_at":{"date":"2019-03-02 15:26:06.000000","timezone_type":3,"timezone":"UTC"},"deleted_at":null},{"id":40,"unique_id":"iKT3acAiVR","name":null,"username":"\u5c71\u7530 \u96f6","email":"soutaro93@example.com","unique_id_search_flag":1,"username_search_flag":1,"join_status":"wait","paid":0,"plus_minus":null,"attribute_name":null,"budget":null,"budget_actual":null,"created_at":{"date":"2019-03-02 15:26:06.000000","timezone_type":3,"timezone":"UTC"},"updated_at":{"date":"2019-03-02 15:26:06.000000","timezone_type":3,"timezone":"UTC"},"deleted_at":null},{"id":48,"unique_id":"CSJXfGzx4w","name":null,"username":"\u30c6\u30b9\u30c8\u30e6\u30fc\u30b6\u30fc\uff12","email":"testuser48@example.com","unique_id_search_flag":1,"username_search_flag":1,"join_status":"allow","paid":1,"plus_minus":null,"attribute_name":null,"budget":null,"budget_actual":null,"created_at":{"date":"2019-03-02 15:26:06.000000","timezone_type":3,"timezone":"UTC"},"updated_at":{"date":"2019-03-02 15:26:28.000000","timezone_type":3,"timezone":"UTC"},"deleted_at":null}],"created_at":{"date":"2019-03-02 15:26:18.000000","timezone_type":3,"timezone":"UTC"},"updated_at":{"date":"2019-03-02 15:26:18.000000","timezone_type":3,"timezone":"UTC"},"deleted_at":null},{"id":112,"name":"quam","shop_id":"J000109445","budget":14030,"actual":31839,"start_time":null,"end_time":null,"unit_rounding_budget":"100","unit_rounding_actual":"100","manager":{"id":34,"unique_id":"qfzTe7qR6n","name":null,"username":"\u5c71\u672c \u5b66","email":"atakahashi@example.org","unique_id_search_flag":1,"username_search_flag":1,"created_at":{"date":"2019-03-02 15:26:06.000000","timezone_type":3,"timezone":"UTC"},"updated_at":{"date":"2019-03-02 15:26:06.000000","timezone_type":3,"timezone":"UTC"},"deleted_at":null},"users":[{"id":7,"unique_id":"CORWNToj6v","name":null,"username":"\u30c6\u30b9\u30c8\u592a\u90ce","email":"testuser@example.com","unique_id_search_flag":1,"username_search_flag":1,"join_status":"deny","paid":0,"plus_minus":null,"attribute_name":null,"budget":null,"budget_actual":null,"created_at":{"date":"2019-03-02 15:26:06.000000","timezone_type":3,"timezone":"UTC"},"updated_at":{"date":"2019-03-02 15:26:28.000000","timezone_type":3,"timezone":"UTC"},"deleted_at":null},{"id":9,"unique_id":"LOewqSn5dZ","name":null,"username":"\u5c0f\u6797 \u592a\u4e00","email":"kudo.yuki@example.net","unique_id_search_flag":1,"username_search_flag":1,"join_status":"allow","paid":1,"plus_minus":null,"attribute_name":null,"budget":null,"budget_actual":null,"created_at":{"date":"2019-03-02 15:26:06.000000","timezone_type":3,"timezone":"UTC"},"updated_at":{"date":"2019-03-02 15:26:06.000000","timezone_type":3,"timezone":"UTC"},"deleted_at":null},{"id":12,"unique_id":"K5fuAg9Wud","name":null,"username":"\u9234\u6728 \u4e03\u590f","email":"momoko58@example.com","unique_id_search_flag":1,"username_search_flag":1,"join_status":"allow","paid":0,"plus_minus":null,"attribute_name":null,"budget":null,"budget_actual":null,"created_at":{"date":"2019-03-02 15:26:06.000000","timezone_type":3,"timezone":"UTC"},"updated_at":{"date":"2019-03-02 15:26:06.000000","timezone_type":3,"timezone":"UTC"},"deleted_at":null},{"id":14,"unique_id":"NUUq5pi71A","name":null,"username":"\u5c71\u53e3 \u88d5\u6a39","email":"watanabe.rika@example.org","unique_id_search_flag":1,"username_search_flag":1,"join_status":"deny","paid":0,"plus_minus":null,"attribute_name":null,"budget":null,"budget_actual":null,"created_at":{"date":"2019-03-02 15:26:06.000000","timezone_type":3,"timezone":"UTC"},"updated_at":{"date":"2019-03-02 15:26:06.000000","timezone_type":3,"timezone":"UTC"},"deleted_at":null},{"id":29,"unique_id":"6x852vmS95","name":null,"username":"\u6d25\u7530 \u9999\u7e54","email":"uno.momoko@example.com","unique_id_search_flag":1,"username_search_flag":1,"join_status":"allow","paid":1,"plus_minus":null,"attribute_name":null,"budget":null,"budget_actual":null,"created_at":{"date":"2019-03-02 15:26:06.000000","timezone_type":3,"timezone":"UTC"},"updated_at":{"date":"2019-03-02 15:26:06.000000","timezone_type":3,"timezone":"UTC"},"deleted_at":null},{"id":39,"unique_id":"I49iMbtdnq","name":null,"username":"\u5c71\u672c \u967d\u5b50","email":"anagisa@example.org","unique_id_search_flag":1,"username_search_flag":1,"join_status":"allow","paid":0,"plus_minus":null,"attribute_name":null,"budget":null,"budget_actual":null,"created_at":{"date":"2019-03-02 15:26:06.000000","timezone_type":3,"timezone":"UTC"},"updated_at":{"date":"2019-03-02 15:26:06.000000","timezone_type":3,"timezone":"UTC"},"deleted_at":null},{"id":44,"unique_id":"ZF5evtBrPn","name":null,"username":"\u52a0\u85e4 \u9999\u7e54","email":"yamamoto.satomi@example.com","unique_id_search_flag":1,"username_search_flag":1,"join_status":"wait","paid":0,"plus_minus":null,"attribute_name":null,"budget":null,"budget_actual":null,"created_at":{"date":"2019-03-02 15:26:06.000000","timezone_type":3,"timezone":"UTC"},"updated_at":{"date":"2019-03-02 15:26:06.000000","timezone_type":3,"timezone":"UTC"},"deleted_at":null}],"created_at":{"date":"2019-03-02 15:26:20.000000","timezone_type":3,"timezone":"UTC"},"updated_at":{"date":"2019-03-02 15:26:20.000000","timezone_type":3,"timezone":"UTC"},"deleted_at":null},{"id":113,"name":"quae","shop_id":"J000449898","budget":12656,"actual":43695,"start_time":"2019-02-25 15:26:20","end_time":null,"unit_rounding_budget":"100","unit_rounding_actual":"100","manager":{"id":34,"unique_id":"qfzTe7qR6n","name":null,"username":"\u5c71\u672c \u5b66","email":"atakahashi@example.org","unique_id_search_flag":1,"username_search_flag":1,"created_at":{"date":"2019-03-02 15:26:06.000000","timezone_type":3,"timezone":"UTC"},"updated_at":{"date":"2019-03-02 15:26:06.000000","timezone_type":3,"timezone":"UTC"},"deleted_at":null},"users":[{"id":7,"unique_id":"CORWNToj6v","name":null,"username":"\u30c6\u30b9\u30c8\u592a\u90ce","email":"testuser@example.com","unique_id_search_flag":1,"username_search_flag":1,"join_status":"wait","paid":0,"plus_minus":null,"attribute_name":null,"budget":null,"budget_actual":null,"created_at":{"date":"2019-03-02 15:26:06.000000","timezone_type":3,"timezone":"UTC"},"updated_at":{"date":"2019-03-02 15:26:28.000000","timezone_type":3,"timezone":"UTC"},"deleted_at":null},{"id":19,"unique_id":"IynP17E7yt","name":null,"username":"\u6751\u5c71 \u9999\u7e54","email":"sasada.miki@example.org","unique_id_search_flag":1,"username_search_flag":1,"join_status":"allow","paid":1,"plus_minus":null,"attribute_name":null,"budget":null,"budget_actual":null,"created_at":{"date":"2019-03-02 15:26:06.000000","timezone_type":3,"timezone":"UTC"},"updated_at":{"date":"2019-03-02 15:26:06.000000","timezone_type":3,"timezone":"UTC"},"deleted_at":null},{"id":29,"unique_id":"6x852vmS95","name":null,"username":"\u6d25\u7530 \u9999\u7e54","email":"uno.momoko@example.com","unique_id_search_flag":1,"username_search_flag":1,"join_status":"wait","paid":0,"plus_minus":null,"attribute_name":null,"budget":null,"budget_actual":null,"created_at":{"date":"2019-03-02 15:26:06.000000","timezone_type":3,"timezone":"UTC"},"updated_at":{"date":"2019-03-02 15:26:06.000000","timezone_type":3,"timezone":"UTC"},"deleted_at":null},{"id":36,"unique_id":"5ambfGXHHq","name":null,"username":"\u4e09\u5b85 \u771f\u7dbe","email":"kimura.mikako@example.com","unique_id_search_flag":1,"username_search_flag":1,"join_status":"wait","paid":0,"plus_minus":null,"attribute_name":null,"budget":null,"budget_actual":null,"created_at":{"date":"2019-03-02 15:26:06.000000","timezone_type":3,"timezone":"UTC"},"updated_at":{"date":"2019-03-02 15:26:06.000000","timezone_type":3,"timezone":"UTC"},"deleted_at":null},{"id":39,"unique_id":"I49iMbtdnq","name":null,"username":"\u5c71\u672c \u967d\u5b50","email":"anagisa@example.org","unique_id_search_flag":1,"username_search_flag":1,"join_status":"allow","paid":0,"plus_minus":null,"attribute_name":null,"budget":null,"budget_actual":null,"created_at":{"date":"2019-03-02 15:26:06.000000","timezone_type":3,"timezone":"UTC"},"updated_at":{"date":"2019-03-02 15:26:06.000000","timezone_type":3,"timezone":"UTC"},"deleted_at":null},{"id":44,"unique_id":"ZF5evtBrPn","name":null,"username":"\u52a0\u85e4 \u9999\u7e54","email":"yamamoto.satomi@example.com","unique_id_search_flag":1,"username_search_flag":1,"join_status":"deny","paid":0,"plus_minus":null,"attribute_name":null,"budget":null,"budget_actual":null,"created_at":{"date":"2019-03-02 15:26:06.000000","timezone_type":3,"timezone":"UTC"},"updated_at":{"date":"2019-03-02 15:26:06.000000","timezone_type":3,"timezone":"UTC"},"deleted_at":null},{"id":50,"unique_id":"XqkDwOOAwI","name":null,"username":"\u30c6\u30b9\u30c8\u30e6\u30fc\u30b6\u30fc\uff13","email":"testuser50@example.com","unique_id_search_flag":1,"username_search_flag":1,"join_status":"deny","paid":0,"plus_minus":null,"attribute_name":null,"budget":null,"budget_actual":null,"created_at":{"date":"2019-03-02 15:26:06.000000","timezone_type":3,"timezone":"UTC"},"updated_at":{"date":"2019-03-02 15:26:28.000000","timezone_type":3,"timezone":"UTC"},"deleted_at":null}],"created_at":{"date":"2019-03-02 15:26:20.000000","timezone_type":3,"timezone":"UTC"},"updated_at":{"date":"2019-03-02 15:26:20.000000","timezone_type":3,"timezone":"UTC"},"deleted_at":null},{"id":129,"name":"sed","shop_id":"J000109445","budget":3475,"actual":7311,"start_time":"2019-02-25 15:26:22","end_time":null,"unit_rounding_budget":"100","unit_rounding_actual":"100","manager":{"id":38,"unique_id":"VUUITRnJwp","name":null,"username":"\u4e95\u4e0a \u304f\u307f\u5b50","email":"chiyo16@example.net","unique_id_search_flag":1,"username_search_flag":1,"created_at":{"date":"2019-03-02 15:26:06.000000","timezone_type":3,"timezone":"UTC"},"updated_at":{"date":"2019-03-02 15:26:06.000000","timezone_type":3,"timezone":"UTC"},"deleted_at":null},"users":[{"id":7,"unique_id":"CORWNToj6v","name":null,"username":"\u30c6\u30b9\u30c8\u592a\u90ce","email":"testuser@example.com","unique_id_search_flag":1,"username_search_flag":1,"join_status":"allow","paid":1,"plus_minus":null,"attribute_name":null,"budget":null,"budget_actual":null,"created_at":{"date":"2019-03-02 15:26:06.000000","timezone_type":3,"timezone":"UTC"},"updated_at":{"date":"2019-03-02 15:26:28.000000","timezone_type":3,"timezone":"UTC"},"deleted_at":null},{"id":13,"unique_id":"bTSVzA4e1b","name":null,"username":"\u5409\u7530 \u7ffc","email":"murayama.ryosuke@example.com","unique_id_search_flag":1,"username_search_flag":1,"join_status":"allow","paid":1,"plus_minus":null,"attribute_name":null,"budget":null,"budget_actual":null,"created_at":{"date":"2019-03-02 15:26:06.000000","timezone_type":3,"timezone":"UTC"},"updated_at":{"date":"2019-03-02 15:26:06.000000","timezone_type":3,"timezone":"UTC"},"deleted_at":null},{"id":16,"unique_id":"jJr2aEhAvx","name":null,"username":"\u9234\u6728 \u5343\u4ee3","email":"murayama.haruka@example.org","unique_id_search_flag":1,"username_search_flag":1,"join_status":"wait","paid":0,"plus_minus":null,"attribute_name":null,"budget":null,"budget_actual":null,"created_at":{"date":"2019-03-02 15:26:06.000000","timezone_type":3,"timezone":"UTC"},"updated_at":{"date":"2019-03-02 15:26:06.000000","timezone_type":3,"timezone":"UTC"},"deleted_at":null},{"id":21,"unique_id":"lSwgexhJGN","name":null,"username":"\u5de5\u85e4 \u76f4\u5b50","email":"enakajima@example.org","unique_id_search_flag":1,"username_search_flag":1,"join_status":"deny","paid":0,"plus_minus":null,"attribute_name":null,"budget":null,"budget_actual":null,"created_at":{"date":"2019-03-02 15:26:06.000000","timezone_type":3,"timezone":"UTC"},"updated_at":{"date":"2019-03-02 15:26:06.000000","timezone_type":3,"timezone":"UTC"},"deleted_at":null}],"created_at":{"date":"2019-03-02 15:26:22.000000","timezone_type":3,"timezone":"UTC"},"updated_at":{"date":"2019-03-02 15:26:22.000000","timezone_type":3,"timezone":"UTC"},"deleted_at":null},{"id":135,"name":"quis","shop_id":"J001125885","budget":17838,"actual":12727,"start_time":"2019-03-07 15:26:23","end_time":"2019-03-12 15:26:23","unit_rounding_budget":"100","unit_rounding_actual":"100","manager":{"id":40,"unique_id":"iKT3acAiVR","name":null,"username":"\u5c71\u7530 \u96f6","email":"soutaro93@example.com","unique_id_search_flag":1,"username_search_flag":1,"created_at":{"date":"2019-03-02 15:26:06.000000","timezone_type":3,"timezone":"UTC"},"updated_at":{"date":"2019-03-02 15:26:06.000000","timezone_type":3,"timezone":"UTC"},"deleted_at":null},"users":[{"id":7,"unique_id":"CORWNToj6v","name":null,"username":"\u30c6\u30b9\u30c8\u592a\u90ce","email":"testuser@example.com","unique_id_search_flag":1,"username_search_flag":1,"join_status":"allow","paid":1,"plus_minus":null,"attribute_name":null,"budget":null,"budget_actual":null,"created_at":{"date":"2019-03-02 15:26:06.000000","timezone_type":3,"timezone":"UTC"},"updated_at":{"date":"2019-03-02 15:26:28.000000","timezone_type":3,"timezone":"UTC"},"deleted_at":null},{"id":8,"unique_id":"YQctNEoTyq","name":null,"username":"\u5409\u672c \u3055\u3086\u308a","email":"akira.yoshida@example.org","unique_id_search_flag":1,"username_search_flag":1,"join_status":"allow","paid":0,"plus_minus":null,"attribute_name":null,"budget":null,"budget_actual":null,"created_at":{"date":"2019-03-02 15:26:06.000000","timezone_type":3,"timezone":"UTC"},"updated_at":{"date":"2019-03-02 15:26:06.000000","timezone_type":3,"timezone":"UTC"},"deleted_at":null},{"id":12,"unique_id":"K5fuAg9Wud","name":null,"username":"\u9234\u6728 \u4e03\u590f","email":"momoko58@example.com","unique_id_search_flag":1,"username_search_flag":1,"join_status":"wait","paid":0,"plus_minus":null,"attribute_name":null,"budget":null,"budget_actual":null,"created_at":{"date":"2019-03-02 15:26:06.000000","timezone_type":3,"timezone":"UTC"},"updated_at":{"date":"2019-03-02 15:26:06.000000","timezone_type":3,"timezone":"UTC"},"deleted_at":null},{"id":36,"unique_id":"5ambfGXHHq","name":null,"username":"\u4e09\u5b85 \u771f\u7dbe","email":"kimura.mikako@example.com","unique_id_search_flag":1,"username_search_flag":1,"join_status":"deny","paid":0,"plus_minus":null,"attribute_name":null,"budget":null,"budget_actual":null,"created_at":{"date":"2019-03-02 15:26:06.000000","timezone_type":3,"timezone":"UTC"},"updated_at":{"date":"2019-03-02 15:26:06.000000","timezone_type":3,"timezone":"UTC"},"deleted_at":null},{"id":38,"unique_id":"VUUITRnJwp","name":null,"username":"\u4e95\u4e0a \u304f\u307f\u5b50","email":"chiyo16@example.net","unique_id_search_flag":1,"username_search_flag":1,"join_status":"allow","paid":1,"plus_minus":null,"attribute_name":null,"budget":null,"budget_actual":null,"created_at":{"date":"2019-03-02 15:26:06.000000","timezone_type":3,"timezone":"UTC"},"updated_at":{"date":"2019-03-02 15:26:06.000000","timezone_type":3,"timezone":"UTC"},"deleted_at":null}],"created_at":{"date":"2019-03-02 15:26:23.000000","timezone_type":3,"timezone":"UTC"},"updated_at":{"date":"2019-03-02 15:26:23.000000","timezone_type":3,"timezone":"UTC"},"deleted_at":null},{"id":137,"name":"odio","shop_id":"J000766202","budget":1031,"actual":44507,"start_time":"2019-02-25 15:26:23","end_time":"2019-03-12 15:26:23","unit_rounding_budget":"100","unit_rounding_actual":"100","manager":{"id":40,"unique_id":"iKT3acAiVR","name":null,"username":"\u5c71\u7530 \u96f6","email":"soutaro93@example.com","unique_id_search_flag":1,"username_search_flag":1,"created_at":{"date":"2019-03-02 15:26:06.000000","timezone_type":3,"timezone":"UTC"},"updated_at":{"date":"2019-03-02 15:26:06.000000","timezone_type":3,"timezone":"UTC"},"deleted_at":null},"users":[{"id":7,"unique_id":"CORWNToj6v","name":null,"username":"\u30c6\u30b9\u30c8\u592a\u90ce","email":"testuser@example.com","unique_id_search_flag":1,"username_search_flag":1,"join_status":"allow","paid":1,"plus_minus":null,"attribute_name":null,"budget":null,"budget_actual":null,"created_at":{"date":"2019-03-02 15:26:06.000000","timezone_type":3,"timezone":"UTC"},"updated_at":{"date":"2019-03-02 15:26:28.000000","timezone_type":3,"timezone":"UTC"},"deleted_at":null},{"id":8,"unique_id":"YQctNEoTyq","name":null,"username":"\u5409\u672c \u3055\u3086\u308a","email":"akira.yoshida@example.org","unique_id_search_flag":1,"username_search_flag":1,"join_status":"allow","paid":1,"plus_minus":null,"attribute_name":null,"budget":null,"budget_actual":null,"created_at":{"date":"2019-03-02 15:26:06.000000","timezone_type":3,"timezone":"UTC"},"updated_at":{"date":"2019-03-02 15:26:06.000000","timezone_type":3,"timezone":"UTC"},"deleted_at":null},{"id":16,"unique_id":"jJr2aEhAvx","name":null,"username":"\u9234\u6728 \u5343\u4ee3","email":"murayama.haruka@example.org","unique_id_search_flag":1,"username_search_flag":1,"join_status":"allow","paid":1,"plus_minus":null,"attribute_name":null,"budget":null,"budget_actual":null,"created_at":{"date":"2019-03-02 15:26:06.000000","timezone_type":3,"timezone":"UTC"},"updated_at":{"date":"2019-03-02 15:26:06.000000","timezone_type":3,"timezone":"UTC"},"deleted_at":null},{"id":27,"unique_id":"0ZmdL4KrQB","name":null,"username":"\u6728\u6751 \u6d69","email":"mitsuru.suzuki@example.com","unique_id_search_flag":1,"username_search_flag":1,"join_status":"deny","paid":0,"plus_minus":null,"attribute_name":null,"budget":null,"budget_actual":null,"created_at":{"date":"2019-03-02 15:26:06.000000","timezone_type":3,"timezone":"UTC"},"updated_at":{"date":"2019-03-02 15:26:06.000000","timezone_type":3,"timezone":"UTC"},"deleted_at":null},{"id":38,"unique_id":"VUUITRnJwp","name":null,"username":"\u4e95\u4e0a \u304f\u307f\u5b50","email":"chiyo16@example.net","unique_id_search_flag":1,"username_search_flag":1,"join_status":"allow","paid":0,"plus_minus":null,"attribute_name":null,"budget":null,"budget_actual":null,"created_at":{"date":"2019-03-02 15:26:06.000000","timezone_type":3,"timezone":"UTC"},"updated_at":{"date":"2019-03-02 15:26:06.000000","timezone_type":3,"timezone":"UTC"},"deleted_at":null}],"created_at":{"date":"2019-03-02 15:26:23.000000","timezone_type":3,"timezone":"UTC"},"updated_at":{"date":"2019-03-02 15:26:23.000000","timezone_type":3,"timezone":"UTC"},"deleted_at":null},{"id":145,"name":"expedita","shop_id":"J000753015","budget":20464,"actual":23795,"start_time":"2019-03-07 15:26:24","end_time":"2019-03-12 15:26:24","unit_rounding_budget":"100","unit_rounding_actual":"100","manager":{"id":42,"unique_id":"WZvU6cXXOp","name":null,"username":"\u539f\u7530 \u821e","email":"taro.suzuki@example.com","unique_id_search_flag":1,"username_search_flag":1,"created_at":{"date":"2019-03-02 15:26:06.000000","timezone_type":3,"timezone":"UTC"},"updated_at":{"date":"2019-03-02 15:26:06.000000","timezone_type":3,"timezone":"UTC"},"deleted_at":null},"users":[{"id":7,"unique_id":"CORWNToj6v","name":null,"username":"\u30c6\u30b9\u30c8\u592a\u90ce","email":"testuser@example.com","unique_id_search_flag":1,"username_search_flag":1,"join_status":"deny","paid":0,"plus_minus":null,"attribute_name":null,"budget":null,"budget_actual":null,"created_at":{"date":"2019-03-02 15:26:06.000000","timezone_type":3,"timezone":"UTC"},"updated_at":{"date":"2019-03-02 15:26:28.000000","timezone_type":3,"timezone":"UTC"},"deleted_at":null},{"id":11,"unique_id":"iIzTTmcOl0","name":null,"username":"\u5c71\u7530 \u660e\u7f8e","email":"ryohei47@example.com","unique_id_search_flag":1,"username_search_flag":1,"join_status":"wait","paid":0,"plus_minus":null,"attribute_name":null,"budget":null,"budget_actual":null,"created_at":{"date":"2019-03-02 15:26:06.000000","timezone_type":3,"timezone":"UTC"},"updated_at":{"date":"2019-03-02 15:26:06.000000","timezone_type":3,"timezone":"UTC"},"deleted_at":null},{"id":19,"unique_id":"IynP17E7yt","name":null,"username":"\u6751\u5c71 \u9999\u7e54","email":"sasada.miki@example.org","unique_id_search_flag":1,"username_search_flag":1,"join_status":"allow","paid":0,"plus_minus":null,"attribute_name":null,"budget":null,"budget_actual":null,"created_at":{"date":"2019-03-02 15:26:06.000000","timezone_type":3,"timezone":"UTC"},"updated_at":{"date":"2019-03-02 15:26:06.000000","timezone_type":3,"timezone":"UTC"},"deleted_at":null},{"id":25,"unique_id":"iogytFIaLq","name":null,"username":"\u4f50\u3005\u6728 \u4fee\u5e73","email":"yui60@example.org","unique_id_search_flag":1,"username_search_flag":1,"join_status":"deny","paid":0,"plus_minus":null,"attribute_name":null,"budget":null,"budget_actual":null,"created_at":{"date":"2019-03-02 15:26:06.000000","timezone_type":3,"timezone":"UTC"},"updated_at":{"date":"2019-03-02 15:26:06.000000","timezone_type":3,"timezone":"UTC"},"deleted_at":null},{"id":31,"unique_id":"Xk5awqONnv","name":null,"username":"\u6d25\u7530 \u77e5\u5b9f","email":"aota.rika@example.com","unique_id_search_flag":1,"username_search_flag":1,"join_status":"wait","paid":0,"plus_minus":null,"attribute_name":null,"budget":null,"budget_actual":null,"created_at":{"date":"2019-03-02 15:26:06.000000","timezone_type":3,"timezone":"UTC"},"updated_at":{"date":"2019-03-02 15:26:06.000000","timezone_type":3,"timezone":"UTC"},"deleted_at":null},{"id":34,"unique_id":"qfzTe7qR6n","name":null,"username":"\u5c71\u672c \u5b66","email":"atakahashi@example.org","unique_id_search_flag":1,"username_search_flag":1,"join_status":"allow","paid":0,"plus_minus":null,"attribute_name":null,"budget":null,"budget_actual":null,"created_at":{"date":"2019-03-02 15:26:06.000000","timezone_type":3,"timezone":"UTC"},"updated_at":{"date":"2019-03-02 15:26:06.000000","timezone_type":3,"timezone":"UTC"},"deleted_at":null},{"id":50,"unique_id":"XqkDwOOAwI","name":null,"username":"\u30c6\u30b9\u30c8\u30e6\u30fc\u30b6\u30fc\uff13","email":"testuser50@example.com","unique_id_search_flag":1,"username_search_flag":1,"join_status":"deny","paid":0,"plus_minus":null,"attribute_name":null,"budget":null,"budget_actual":null,"created_at":{"date":"2019-03-02 15:26:06.000000","timezone_type":3,"timezone":"UTC"},"updated_at":{"date":"2019-03-02 15:26:28.000000","timezone_type":3,"timezone":"UTC"},"deleted_at":null}],"created_at":{"date":"2019-03-02 15:26:24.000000","timezone_type":3,"timezone":"UTC"},"updated_at":{"date":"2019-03-02 15:26:24.000000","timezone_type":3,"timezone":"UTC"},"deleted_at":null},{"id":154,"name":"et","shop_id":"J000753015","budget":17225,"actual":21732,"start_time":"2019-02-20 15:26:25","end_time":"2019-02-25 15:26:25","unit_rounding_budget":"100","unit_rounding_actual":"100","manager":{"id":45,"unique_id":"WqZoj7f9dl","name":null,"username":"\u5409\u672c \u5e79","email":"yamagishi.osamu@example.net","unique_id_search_flag":1,"username_search_flag":1,"created_at":{"date":"2019-03-02 15:26:06.000000","timezone_type":3,"timezone":"UTC"},"updated_at":{"date":"2019-03-02 15:26:06.000000","timezone_type":3,"timezone":"UTC"},"deleted_at":null},"users":[{"id":7,"unique_id":"CORWNToj6v","name":null,"username":"\u30c6\u30b9\u30c8\u592a\u90ce","email":"testuser@example.com","unique_id_search_flag":1,"username_search_flag":1,"join_status":"allow","paid":0,"plus_minus":null,"attribute_name":null,"budget":null,"budget_actual":null,"created_at":{"date":"2019-03-02 15:26:06.000000","timezone_type":3,"timezone":"UTC"},"updated_at":{"date":"2019-03-02 15:26:28.000000","timezone_type":3,"timezone":"UTC"},"deleted_at":null},{"id":14,"unique_id":"NUUq5pi71A","name":null,"username":"\u5c71\u53e3 \u88d5\u6a39","email":"watanabe.rika@example.org","unique_id_search_flag":1,"username_search_flag":1,"join_status":"allow","paid":0,"plus_minus":null,"attribute_name":null,"budget":null,"budget_actual":null,"created_at":{"date":"2019-03-02 15:26:06.000000","timezone_type":3,"timezone":"UTC"},"updated_at":{"date":"2019-03-02 15:26:06.000000","timezone_type":3,"timezone":"UTC"},"deleted_at":null},{"id":17,"unique_id":"0zEcDc0oVd","name":null,"username":"\u6d25\u7530 \u7d50\u8863","email":"hideki.kobayashi@example.org","unique_id_search_flag":1,"username_search_flag":1,"join_status":"allow","paid":0,"plus_minus":null,"attribute_name":null,"budget":null,"budget_actual":null,"created_at":{"date":"2019-03-02 15:26:06.000000","timezone_type":3,"timezone":"UTC"},"updated_at":{"date":"2019-03-02 15:26:06.000000","timezone_type":3,"timezone":"UTC"},"deleted_at":null},{"id":21,"unique_id":"lSwgexhJGN","name":null,"username":"\u5de5\u85e4 \u76f4\u5b50","email":"enakajima@example.org","unique_id_search_flag":1,"username_search_flag":1,"join_status":"deny","paid":0,"plus_minus":null,"attribute_name":null,"budget":null,"budget_actual":null,"created_at":{"date":"2019-03-02 15:26:06.000000","timezone_type":3,"timezone":"UTC"},"updated_at":{"date":"2019-03-02 15:26:06.000000","timezone_type":3,"timezone":"UTC"},"deleted_at":null},{"id":23,"unique_id":"jFW6MAPaHw","name":null,"username":"\u6728\u6751 \u3042\u3059\u304b","email":"ryosuke20@example.org","unique_id_search_flag":1,"username_search_flag":1,"join_status":"wait","paid":0,"plus_minus":null,"attribute_name":null,"budget":null,"budget_actual":null,"created_at":{"date":"2019-03-02 15:26:06.000000","timezone_type":3,"timezone":"UTC"},"updated_at":{"date":"2019-03-02 15:26:06.000000","timezone_type":3,"timezone":"UTC"},"deleted_at":null},{"id":25,"unique_id":"iogytFIaLq","name":null,"username":"\u4f50\u3005\u6728 \u4fee\u5e73","email":"yui60@example.org","unique_id_search_flag":1,"username_search_flag":1,"join_status":"deny","paid":0,"plus_minus":null,"attribute_name":null,"budget":null,"budget_actual":null,"created_at":{"date":"2019-03-02 15:26:06.000000","timezone_type":3,"timezone":"UTC"},"updated_at":{"date":"2019-03-02 15:26:06.000000","timezone_type":3,"timezone":"UTC"},"deleted_at":null},{"id":28,"unique_id":"zsVDfRCOya","name":null,"username":"\u52a0\u85e4 \u4eac\u52a9","email":"kudo.mitsuru@example.net","unique_id_search_flag":1,"username_search_flag":1,"join_status":"deny","paid":0,"plus_minus":null,"attribute_name":null,"budget":null,"budget_actual":null,"created_at":{"date":"2019-03-02 15:26:06.000000","timezone_type":3,"timezone":"UTC"},"updated_at":{"date":"2019-03-02 15:26:06.000000","timezone_type":3,"timezone":"UTC"},"deleted_at":null},{"id":30,"unique_id":"Lat0uC4PeV","name":null,"username":"\u5c71\u7530 \u3055\u3086\u308a","email":"shota.takahashi@example.com","unique_id_search_flag":1,"username_search_flag":1,"join_status":"deny","paid":0,"plus_minus":null,"attribute_name":null,"budget":null,"budget_actual":null,"created_at":{"date":"2019-03-02 15:26:06.000000","timezone_type":3,"timezone":"UTC"},"updated_at":{"date":"2019-03-02 15:26:06.000000","timezone_type":3,"timezone":"UTC"},"deleted_at":null},{"id":48,"unique_id":"CSJXfGzx4w","name":null,"username":"\u30c6\u30b9\u30c8\u30e6\u30fc\u30b6\u30fc\uff12","email":"testuser48@example.com","unique_id_search_flag":1,"username_search_flag":1,"join_status":"deny","paid":0,"plus_minus":null,"attribute_name":null,"budget":null,"budget_actual":null,"created_at":{"date":"2019-03-02 15:26:06.000000","timezone_type":3,"timezone":"UTC"},"updated_at":{"date":"2019-03-02 15:26:28.000000","timezone_type":3,"timezone":"UTC"},"deleted_at":null}],"created_at":{"date":"2019-03-02 15:26:25.000000","timezone_type":3,"timezone":"UTC"},"updated_at":{"date":"2019-03-02 15:26:25.000000","timezone_type":3,"timezone":"UTC"},"deleted_at":null},{"id":156,"name":"qui","shop_id":"J001125885","budget":24408,"actual":35067,"start_time":"2019-02-25 15:26:25","end_time":null,"unit_rounding_budget":"100","unit_rounding_actual":"100","manager":{"id":45,"unique_id":"WqZoj7f9dl","name":null,"username":"\u5409\u672c \u5e79","email":"yamagishi.osamu@example.net","unique_id_search_flag":1,"username_search_flag":1,"created_at":{"date":"2019-03-02 15:26:06.000000","timezone_type":3,"timezone":"UTC"},"updated_at":{"date":"2019-03-02 15:26:06.000000","timezone_type":3,"timezone":"UTC"},"deleted_at":null},"users":[{"id":7,"unique_id":"CORWNToj6v","name":null,"username":"\u30c6\u30b9\u30c8\u592a\u90ce","email":"testuser@example.com","unique_id_search_flag":1,"username_search_flag":1,"join_status":"allow","paid":0,"plus_minus":null,"attribute_name":null,"budget":null,"budget_actual":null,"created_at":{"date":"2019-03-02 15:26:06.000000","timezone_type":3,"timezone":"UTC"},"updated_at":{"date":"2019-03-02 15:26:28.000000","timezone_type":3,"timezone":"UTC"},"deleted_at":null},{"id":20,"unique_id":"eGwHjPernR","name":null,"username":"\u91ce\u6751 \u76f4\u4eba","email":"takuma.saito@example.net","unique_id_search_flag":1,"username_search_flag":1,"join_status":"wait","paid":0,"plus_minus":null,"attribute_name":null,"budget":null,"budget_actual":null,"created_at":{"date":"2019-03-02 15:26:06.000000","timezone_type":3,"timezone":"UTC"},"updated_at":{"date":"2019-03-02 15:26:06.000000","timezone_type":3,"timezone":"UTC"},"deleted_at":null},{"id":23,"unique_id":"jFW6MAPaHw","name":null,"username":"\u6728\u6751 \u3042\u3059\u304b","email":"ryosuke20@example.org","unique_id_search_flag":1,"username_search_flag":1,"join_status":"deny","paid":0,"plus_minus":null,"attribute_name":null,"budget":null,"budget_actual":null,"created_at":{"date":"2019-03-02 15:26:06.000000","timezone_type":3,"timezone":"UTC"},"updated_at":{"date":"2019-03-02 15:26:06.000000","timezone_type":3,"timezone":"UTC"},"deleted_at":null},{"id":25,"unique_id":"iogytFIaLq","name":null,"username":"\u4f50\u3005\u6728 \u4fee\u5e73","email":"yui60@example.org","unique_id_search_flag":1,"username_search_flag":1,"join_status":"wait","paid":0,"plus_minus":null,"attribute_name":null,"budget":null,"budget_actual":null,"created_at":{"date":"2019-03-02 15:26:06.000000","timezone_type":3,"timezone":"UTC"},"updated_at":{"date":"2019-03-02 15:26:06.000000","timezone_type":3,"timezone":"UTC"},"deleted_at":null},{"id":26,"unique_id":"ocbTn0ylwc","name":null,"username":"\u6850\u5c71 \u967d\u4e00","email":"pnakamura@example.net","unique_id_search_flag":1,"username_search_flag":1,"join_status":"wait","paid":0,"plus_minus":null,"attribute_name":null,"budget":null,"budget_actual":null,"created_at":{"date":"2019-03-02 15:26:06.000000","timezone_type":3,"timezone":"UTC"},"updated_at":{"date":"2019-03-02 15:26:06.000000","timezone_type":3,"timezone":"UTC"},"deleted_at":null},{"id":38,"unique_id":"VUUITRnJwp","name":null,"username":"\u4e95\u4e0a \u304f\u307f\u5b50","email":"chiyo16@example.net","unique_id_search_flag":1,"username_search_flag":1,"join_status":"wait","paid":0,"plus_minus":null,"attribute_name":null,"budget":null,"budget_actual":null,"created_at":{"date":"2019-03-02 15:26:06.000000","timezone_type":3,"timezone":"UTC"},"updated_at":{"date":"2019-03-02 15:26:06.000000","timezone_type":3,"timezone":"UTC"},"deleted_at":null},{"id":47,"unique_id":"FwHeEEyOFe","name":null,"username":"\u5bae\u6ca2 \u52a0\u5948","email":"satomi25@example.net","unique_id_search_flag":1,"username_search_flag":1,"join_status":"allow","paid":0,"plus_minus":null,"attribute_name":null,"budget":null,"budget_actual":null,"created_at":{"date":"2019-03-02 15:26:06.000000","timezone_type":3,"timezone":"UTC"},"updated_at":{"date":"2019-03-02 15:26:06.000000","timezone_type":3,"timezone":"UTC"},"deleted_at":null},{"id":48,"unique_id":"CSJXfGzx4w","name":null,"username":"\u30c6\u30b9\u30c8\u30e6\u30fc\u30b6\u30fc\uff12","email":"testuser48@example.com","unique_id_search_flag":1,"username_search_flag":1,"join_status":"wait","paid":0,"plus_minus":null,"attribute_name":null,"budget":null,"budget_actual":null,"created_at":{"date":"2019-03-02 15:26:06.000000","timezone_type":3,"timezone":"UTC"},"updated_at":{"date":"2019-03-02 15:26:28.000000","timezone_type":3,"timezone":"UTC"},"deleted_at":null},{"id":50,"unique_id":"XqkDwOOAwI","name":null,"username":"\u30c6\u30b9\u30c8\u30e6\u30fc\u30b6\u30fc\uff13","email":"testuser50@example.com","unique_id_search_flag":1,"username_search_flag":1,"join_status":"deny","paid":0,"plus_minus":null,"attribute_name":null,"budget":null,"budget_actual":null,"created_at":{"date":"2019-03-02 15:26:06.000000","timezone_type":3,"timezone":"UTC"},"updated_at":{"date":"2019-03-02 15:26:28.000000","timezone_type":3,"timezone":"UTC"},"deleted_at":null}],"created_at":{"date":"2019-03-02 15:26:25.000000","timezone_type":3,"timezone":"UTC"},"updated_at":{"date":"2019-03-02 15:26:25.000000","timezone_type":3,"timezone":"UTC"},"deleted_at":null},{"id":157,"name":"provident","shop_id":"J001006387","budget":9352,"actual":7559,"start_time":"2019-02-25 15:26:25","end_time":null,"unit_rounding_budget":"100","unit_rounding_actual":"100","manager":{"id":45,"unique_id":"WqZoj7f9dl","name":null,"username":"\u5409\u672c \u5e79","email":"yamagishi.osamu@example.net","unique_id_search_flag":1,"username_search_flag":1,"created_at":{"date":"2019-03-02 15:26:06.000000","timezone_type":3,"timezone":"UTC"},"updated_at":{"date":"2019-03-02 15:26:06.000000","timezone_type":3,"timezone":"UTC"},"deleted_at":null},"users":[{"id":7,"unique_id":"CORWNToj6v","name":null,"username":"\u30c6\u30b9\u30c8\u592a\u90ce","email":"testuser@example.com","unique_id_search_flag":1,"username_search_flag":1,"join_status":"allow","paid":1,"plus_minus":null,"attribute_name":null,"budget":null,"budget_actual":null,"created_at":{"date":"2019-03-02 15:26:06.000000","timezone_type":3,"timezone":"UTC"},"updated_at":{"date":"2019-03-02 15:26:28.000000","timezone_type":3,"timezone":"UTC"},"deleted_at":null},{"id":14,"unique_id":"NUUq5pi71A","name":null,"username":"\u5c71\u53e3 \u88d5\u6a39","email":"watanabe.rika@example.org","unique_id_search_flag":1,"username_search_flag":1,"join_status":"wait","paid":0,"plus_minus":null,"attribute_name":null,"budget":null,"budget_actual":null,"created_at":{"date":"2019-03-02 15:26:06.000000","timezone_type":3,"timezone":"UTC"},"updated_at":{"date":"2019-03-02 15:26:06.000000","timezone_type":3,"timezone":"UTC"},"deleted_at":null},{"id":17,"unique_id":"0zEcDc0oVd","name":null,"username":"\u6d25\u7530 \u7d50\u8863","email":"hideki.kobayashi@example.org","unique_id_search_flag":1,"username_search_flag":1,"join_status":"allow","paid":1,"plus_minus":null,"attribute_name":null,"budget":null,"budget_actual":null,"created_at":{"date":"2019-03-02 15:26:06.000000","timezone_type":3,"timezone":"UTC"},"updated_at":{"date":"2019-03-02 15:26:06.000000","timezone_type":3,"timezone":"UTC"},"deleted_at":null},{"id":20,"unique_id":"eGwHjPernR","name":null,"username":"\u91ce\u6751 \u76f4\u4eba","email":"takuma.saito@example.net","unique_id_search_flag":1,"username_search_flag":1,"join_status":"deny","paid":0,"plus_minus":null,"attribute_name":null,"budget":null,"budget_actual":null,"created_at":{"date":"2019-03-02 15:26:06.000000","timezone_type":3,"timezone":"UTC"},"updated_at":{"date":"2019-03-02 15:26:06.000000","timezone_type":3,"timezone":"UTC"},"deleted_at":null},{"id":23,"unique_id":"jFW6MAPaHw","name":null,"username":"\u6728\u6751 \u3042\u3059\u304b","email":"ryosuke20@example.org","unique_id_search_flag":1,"username_search_flag":1,"join_status":"deny","paid":0,"plus_minus":null,"attribute_name":null,"budget":null,"budget_actual":null,"created_at":{"date":"2019-03-02 15:26:06.000000","timezone_type":3,"timezone":"UTC"},"updated_at":{"date":"2019-03-02 15:26:06.000000","timezone_type":3,"timezone":"UTC"},"deleted_at":null},{"id":25,"unique_id":"iogytFIaLq","name":null,"username":"\u4f50\u3005\u6728 \u4fee\u5e73","email":"yui60@example.org","unique_id_search_flag":1,"username_search_flag":1,"join_status":"deny","paid":0,"plus_minus":null,"attribute_name":null,"budget":null,"budget_actual":null,"created_at":{"date":"2019-03-02 15:26:06.000000","timezone_type":3,"timezone":"UTC"},"updated_at":{"date":"2019-03-02 15:26:06.000000","timezone_type":3,"timezone":"UTC"},"deleted_at":null},{"id":29,"unique_id":"6x852vmS95","name":null,"username":"\u6d25\u7530 \u9999\u7e54","email":"uno.momoko@example.com","unique_id_search_flag":1,"username_search_flag":1,"join_status":"wait","paid":0,"plus_minus":null,"attribute_name":null,"budget":null,"budget_actual":null,"created_at":{"date":"2019-03-02 15:26:06.000000","timezone_type":3,"timezone":"UTC"},"updated_at":{"date":"2019-03-02 15:26:06.000000","timezone_type":3,"timezone":"UTC"},"deleted_at":null},{"id":38,"unique_id":"VUUITRnJwp","name":null,"username":"\u4e95\u4e0a \u304f\u307f\u5b50","email":"chiyo16@example.net","unique_id_search_flag":1,"username_search_flag":1,"join_status":"wait","paid":0,"plus_minus":null,"attribute_name":null,"budget":null,"budget_actual":null,"created_at":{"date":"2019-03-02 15:26:06.000000","timezone_type":3,"timezone":"UTC"},"updated_at":{"date":"2019-03-02 15:26:06.000000","timezone_type":3,"timezone":"UTC"},"deleted_at":null},{"id":47,"unique_id":"FwHeEEyOFe","name":null,"username":"\u5bae\u6ca2 \u52a0\u5948","email":"satomi25@example.net","unique_id_search_flag":1,"username_search_flag":1,"join_status":"deny","paid":0,"plus_minus":null,"attribute_name":null,"budget":null,"budget_actual":null,"created_at":{"date":"2019-03-02 15:26:06.000000","timezone_type":3,"timezone":"UTC"},"updated_at":{"date":"2019-03-02 15:26:06.000000","timezone_type":3,"timezone":"UTC"},"deleted_at":null}],"created_at":{"date":"2019-03-02 15:26:25.000000","timezone_type":3,"timezone":"UTC"},"updated_at":{"date":"2019-03-02 15:26:25.000000","timezone_type":3,"timezone":"UTC"},"deleted_at":null},{"id":166,"name":"nobis","shop_id":"J000449898","budget":15403,"actual":15681,"start_time":"2019-03-07 15:26:27","end_time":"2019-03-12 15:26:27","unit_rounding_budget":"100","unit_rounding_actual":"100","manager":{"id":48,"unique_id":"CSJXfGzx4w","name":null,"username":"\u30c6\u30b9\u30c8\u30e6\u30fc\u30b6\u30fc\uff12","email":"testuser48@example.com","unique_id_search_flag":1,"username_search_flag":1,"created_at":{"date":"2019-03-02 15:26:06.000000","timezone_type":3,"timezone":"UTC"},"updated_at":{"date":"2019-03-02 15:26:28.000000","timezone_type":3,"timezone":"UTC"},"deleted_at":null},"users":[{"id":7,"unique_id":"CORWNToj6v","name":null,"username":"\u30c6\u30b9\u30c8\u592a\u90ce","email":"testuser@example.com","unique_id_search_flag":1,"username_search_flag":1,"join_status":"wait","paid":0,"plus_minus":null,"attribute_name":null,"budget":null,"budget_actual":null,"created_at":{"date":"2019-03-02 15:26:06.000000","timezone_type":3,"timezone":"UTC"},"updated_at":{"date":"2019-03-02 15:26:28.000000","timezone_type":3,"timezone":"UTC"},"deleted_at":null},{"id":8,"unique_id":"YQctNEoTyq","name":null,"username":"\u5409\u672c \u3055\u3086\u308a","email":"akira.yoshida@example.org","unique_id_search_flag":1,"username_search_flag":1,"join_status":"allow","paid":1,"plus_minus":null,"attribute_name":null,"budget":null,"budget_actual":null,"created_at":{"date":"2019-03-02 15:26:06.000000","timezone_type":3,"timezone":"UTC"},"updated_at":{"date":"2019-03-02 15:26:06.000000","timezone_type":3,"timezone":"UTC"},"deleted_at":null},{"id":21,"unique_id":"lSwgexhJGN","name":null,"username":"\u5de5\u85e4 \u76f4\u5b50","email":"enakajima@example.org","unique_id_search_flag":1,"username_search_flag":1,"join_status":"wait","paid":0,"plus_minus":null,"attribute_name":null,"budget":null,"budget_actual":null,"created_at":{"date":"2019-03-02 15:26:06.000000","timezone_type":3,"timezone":"UTC"},"updated_at":{"date":"2019-03-02 15:26:06.000000","timezone_type":3,"timezone":"UTC"},"deleted_at":null},{"id":29,"unique_id":"6x852vmS95","name":null,"username":"\u6d25\u7530 \u9999\u7e54","email":"uno.momoko@example.com","unique_id_search_flag":1,"username_search_flag":1,"join_status":"deny","paid":0,"plus_minus":null,"attribute_name":null,"budget":null,"budget_actual":null,"created_at":{"date":"2019-03-02 15:26:06.000000","timezone_type":3,"timezone":"UTC"},"updated_at":{"date":"2019-03-02 15:26:06.000000","timezone_type":3,"timezone":"UTC"},"deleted_at":null},{"id":40,"unique_id":"iKT3acAiVR","name":null,"username":"\u5c71\u7530 \u96f6","email":"soutaro93@example.com","unique_id_search_flag":1,"username_search_flag":1,"join_status":"deny","paid":0,"plus_minus":null,"attribute_name":null,"budget":null,"budget_actual":null,"created_at":{"date":"2019-03-02 15:26:06.000000","timezone_type":3,"timezone":"UTC"},"updated_at":{"date":"2019-03-02 15:26:06.000000","timezone_type":3,"timezone":"UTC"},"deleted_at":null},{"id":45,"unique_id":"WqZoj7f9dl","name":null,"username":"\u5409\u672c \u5e79","email":"yamagishi.osamu@example.net","unique_id_search_flag":1,"username_search_flag":1,"join_status":"deny","paid":0,"plus_minus":null,"attribute_name":null,"budget":null,"budget_actual":null,"created_at":{"date":"2019-03-02 15:26:06.000000","timezone_type":3,"timezone":"UTC"},"updated_at":{"date":"2019-03-02 15:26:06.000000","timezone_type":3,"timezone":"UTC"},"deleted_at":null}],"created_at":{"date":"2019-03-02 15:26:27.000000","timezone_type":3,"timezone":"UTC"},"updated_at":{"date":"2019-03-02 15:26:27.000000","timezone_type":3,"timezone":"UTC"},"deleted_at":null},{"id":167,"name":"doloribus","shop_id":"J000753015","budget":21143,"actual":12913,"start_time":null,"end_time":null,"unit_rounding_budget":"100","unit_rounding_actual":"100","manager":{"id":48,"unique_id":"CSJXfGzx4w","name":null,"username":"\u30c6\u30b9\u30c8\u30e6\u30fc\u30b6\u30fc\uff12","email":"testuser48@example.com","unique_id_search_flag":1,"username_search_flag":1,"created_at":{"date":"2019-03-02 15:26:06.000000","timezone_type":3,"timezone":"UTC"},"updated_at":{"date":"2019-03-02 15:26:28.000000","timezone_type":3,"timezone":"UTC"},"deleted_at":null},"users":[{"id":7,"unique_id":"CORWNToj6v","name":null,"username":"\u30c6\u30b9\u30c8\u592a\u90ce","email":"testuser@example.com","unique_id_search_flag":1,"username_search_flag":1,"join_status":"wait","paid":0,"plus_minus":null,"attribute_name":null,"budget":null,"budget_actual":null,"created_at":{"date":"2019-03-02 15:26:06.000000","timezone_type":3,"timezone":"UTC"},"updated_at":{"date":"2019-03-02 15:26:28.000000","timezone_type":3,"timezone":"UTC"},"deleted_at":null},{"id":8,"unique_id":"YQctNEoTyq","name":null,"username":"\u5409\u672c \u3055\u3086\u308a","email":"akira.yoshida@example.org","unique_id_search_flag":1,"username_search_flag":1,"join_status":"allow","paid":1,"plus_minus":null,"attribute_name":null,"budget":null,"budget_actual":null,"created_at":{"date":"2019-03-02 15:26:06.000000","timezone_type":3,"timezone":"UTC"},"updated_at":{"date":"2019-03-02 15:26:06.000000","timezone_type":3,"timezone":"UTC"},"deleted_at":null},{"id":15,"unique_id":"7U2vUA0YvN","name":null,"username":"\u4f0a\u85e4 \u7d50\u8863","email":"juno@example.org","unique_id_search_flag":1,"username_search_flag":1,"join_status":"deny","paid":0,"plus_minus":null,"attribute_name":null,"budget":null,"budget_actual":null,"created_at":{"date":"2019-03-02 15:26:06.000000","timezone_type":3,"timezone":"UTC"},"updated_at":{"date":"2019-03-02 15:26:06.000000","timezone_type":3,"timezone":"UTC"},"deleted_at":null},{"id":40,"unique_id":"iKT3acAiVR","name":null,"username":"\u5c71\u7530 \u96f6","email":"soutaro93@example.com","unique_id_search_flag":1,"username_search_flag":1,"join_status":"wait","paid":0,"plus_minus":null,"attribute_name":null,"budget":null,"budget_actual":null,"created_at":{"date":"2019-03-02 15:26:06.000000","timezone_type":3,"timezone":"UTC"},"updated_at":{"date":"2019-03-02 15:26:06.000000","timezone_type":3,"timezone":"UTC"},"deleted_at":null},{"id":41,"unique_id":"wvlmebsblv","name":null,"username":"\u85e4\u672c \u6dbc\u5e73","email":"wmatsumoto@example.org","unique_id_search_flag":1,"username_search_flag":1,"join_status":"wait","paid":0,"plus_minus":null,"attribute_name":null,"budget":null,"budget_actual":null,"created_at":{"date":"2019-03-02 15:26:06.000000","timezone_type":3,"timezone":"UTC"},"updated_at":{"date":"2019-03-02 15:26:06.000000","timezone_type":3,"timezone":"UTC"},"deleted_at":null},{"id":43,"unique_id":"oYqZdydCO9","name":null,"username":"\u52a0\u85e4 \u88d5\u6a39","email":"kenichi38@example.net","unique_id_search_flag":1,"username_search_flag":1,"join_status":"wait","paid":0,"plus_minus":null,"attribute_name":null,"budget":null,"budget_actual":null,"created_at":{"date":"2019-03-02 15:26:06.000000","timezone_type":3,"timezone":"UTC"},"updated_at":{"date":"2019-03-02 15:26:06.000000","timezone_type":3,"timezone":"UTC"},"deleted_at":null}],"created_at":{"date":"2019-03-02 15:26:27.000000","timezone_type":3,"timezone":"UTC"},"updated_at":{"date":"2019-03-02 15:26:27.000000","timezone_type":3,"timezone":"UTC"},"deleted_at":null},{"id":169,"name":"sit","shop_id":"J001178400","budget":14806,"actual":14367,"start_time":"2019-02-25 15:26:27","end_time":null,"unit_rounding_budget":"100","unit_rounding_actual":"100","manager":{"id":48,"unique_id":"CSJXfGzx4w","name":null,"username":"\u30c6\u30b9\u30c8\u30e6\u30fc\u30b6\u30fc\uff12","email":"testuser48@example.com","unique_id_search_flag":1,"username_search_flag":1,"created_at":{"date":"2019-03-02 15:26:06.000000","timezone_type":3,"timezone":"UTC"},"updated_at":{"date":"2019-03-02 15:26:28.000000","timezone_type":3,"timezone":"UTC"},"deleted_at":null},"users":[{"id":7,"unique_id":"CORWNToj6v","name":null,"username":"\u30c6\u30b9\u30c8\u592a\u90ce","email":"testuser@example.com","unique_id_search_flag":1,"username_search_flag":1,"join_status":"allow","paid":0,"plus_minus":null,"attribute_name":null,"budget":null,"budget_actual":null,"created_at":{"date":"2019-03-02 15:26:06.000000","timezone_type":3,"timezone":"UTC"},"updated_at":{"date":"2019-03-02 15:26:28.000000","timezone_type":3,"timezone":"UTC"},"deleted_at":null},{"id":8,"unique_id":"YQctNEoTyq","name":null,"username":"\u5409\u672c \u3055\u3086\u308a","email":"akira.yoshida@example.org","unique_id_search_flag":1,"username_search_flag":1,"join_status":"wait","paid":0,"plus_minus":null,"attribute_name":null,"budget":null,"budget_actual":null,"created_at":{"date":"2019-03-02 15:26:06.000000","timezone_type":3,"timezone":"UTC"},"updated_at":{"date":"2019-03-02 15:26:06.000000","timezone_type":3,"timezone":"UTC"},"deleted_at":null},{"id":21,"unique_id":"lSwgexhJGN","name":null,"username":"\u5de5\u85e4 \u76f4\u5b50","email":"enakajima@example.org","unique_id_search_flag":1,"username_search_flag":1,"join_status":"wait","paid":0,"plus_minus":null,"attribute_name":null,"budget":null,"budget_actual":null,"created_at":{"date":"2019-03-02 15:26:06.000000","timezone_type":3,"timezone":"UTC"},"updated_at":{"date":"2019-03-02 15:26:06.000000","timezone_type":3,"timezone":"UTC"},"deleted_at":null},{"id":29,"unique_id":"6x852vmS95","name":null,"username":"\u6d25\u7530 \u9999\u7e54","email":"uno.momoko@example.com","unique_id_search_flag":1,"username_search_flag":1,"join_status":"wait","paid":0,"plus_minus":null,"attribute_name":null,"budget":null,"budget_actual":null,"created_at":{"date":"2019-03-02 15:26:06.000000","timezone_type":3,"timezone":"UTC"},"updated_at":{"date":"2019-03-02 15:26:06.000000","timezone_type":3,"timezone":"UTC"},"deleted_at":null},{"id":31,"unique_id":"Xk5awqONnv","name":null,"username":"\u6d25\u7530 \u77e5\u5b9f","email":"aota.rika@example.com","unique_id_search_flag":1,"username_search_flag":1,"join_status":"deny","paid":0,"plus_minus":null,"attribute_name":null,"budget":null,"budget_actual":null,"created_at":{"date":"2019-03-02 15:26:06.000000","timezone_type":3,"timezone":"UTC"},"updated_at":{"date":"2019-03-02 15:26:06.000000","timezone_type":3,"timezone":"UTC"},"deleted_at":null},{"id":38,"unique_id":"VUUITRnJwp","name":null,"username":"\u4e95\u4e0a \u304f\u307f\u5b50","email":"chiyo16@example.net","unique_id_search_flag":1,"username_search_flag":1,"join_status":"wait","paid":0,"plus_minus":null,"attribute_name":null,"budget":null,"budget_actual":null,"created_at":{"date":"2019-03-02 15:26:06.000000","timezone_type":3,"timezone":"UTC"},"updated_at":{"date":"2019-03-02 15:26:06.000000","timezone_type":3,"timezone":"UTC"},"deleted_at":null}],"created_at":{"date":"2019-03-02 15:26:27.000000","timezone_type":3,"timezone":"UTC"},"updated_at":{"date":"2019-03-02 15:26:27.000000","timezone_type":3,"timezone":"UTC"},"deleted_at":null}]}